Workbook

Sheet Plano
A1: ID do plano | B1: Nome do plano | C1: Data da exportação
A2: fHewUC8uj0ioRbpAX8PFEmQADhut | B2: Gestão MEG | C2: 2026-08-15

Sheet Dados Consolidados
A1: Identificação da tarefa | B1: Nome da tarefa | C1: Categoria | D1: Meta | E1: Status | F1: Prioridade | G1: Atribuído a | H1: Criado por | I1: Criado em | J1: Data de conclusão | K1: Data de início | L1: É Recorrente | M1: Atrasados | N1: Concluído em | O1: Concluída por | P1: Itens concluídos da lista de verificação | Q1: Itens da lista de verificação | R1: Rótulos | S1: Notas | T1: Orçamento
A2: mHYaQDYxrUiQ7uHDBJV_CGQAA0Bm | B2: Lançar melhoria do bimestre | C2: =_xlfn.XLOOKUP(A2,Tarefas!A:A,Tarefas!C:C) -> Programa de Melhorias | E2: Não iniciado | F2: Média | G2: Francisco Romulo de Aguiar;;William Kennedy Rodrigues Lopes;Francisco Martins da Silva;Charliane Batista de Alencar | H2: Francisco Romulo de Aguiar | I2: 2026-08-06 | J2: 2026-10-05 | M2: false | P2: 0/10 | Q2: Rômulo ;Charliane;Thiago Roberto;Martins;Leonardo Galdino;Kennedy;Leonardo Costa;Eduarda;Daniel Viana;Alan Vilela | T2: 880.64
A3: epEHIZFoYEawEMf2UmdnO2QAEl9u | B3: Lançar melhoria do bimestre | C3: =_xlfn.XLOOKUP(A3,Tarefas!A:A,Tarefas!C:C) -> Programa de Melhorias | E3: Concluída | F3: Média | G3: Francisco Romulo de Aguiar;;William Kennedy Rodrigues Lopes;Francisco Martins da Silva;Charliane Batista de Alencar | H3: Fernanda Sousa Araujo | I3: 2026-07-17 | J3: 2026-08-05 | M3: false | N3: 2026-08-06 | O3: Francisco Romulo de Aguiar | P3: 7/10 | Q3: Rômulo ;Charliane;Thiago Roberto;Martins;Leonardo Galdino;Kennedy;Leonardo Costa;Eduarda;Daniel Viana;Alan Vilela | T3: 321.55
A4: 7SBLlTg6NUODyqgmnqwBnmQAPYN6 | B4: Lançar melhoria do bimestre | C4: =_xlfn.XLOOKUP(A4,Tarefas!A:A,Tarefas!C:C) -> Programa de Melhorias | E4: Concluída | F4: Média | G4: Francisco Romulo de Aguiar;;;William Kennedy Rodrigues Lopes;Francisco Martins da Silva;Charliane Batista de Alencar | H4: Fernanda Sousa Araujo | I4: 2026-07-17 | J4: 2026-04-05 | M4: false | N4: 2026-07-17 | O4: Fernanda Sousa Araujo | P4: 0/6 | Q4: Rômulo ;Charliane;Martins;Kennedy;Douglas;Jennifer | T4: 560.77
A5: DRYwgOUmRUOgKzjzalMjq2QAAtiM | B5: Lançar melhoria do bimestre | C5: =_xlfn.XLOOKUP(A5,Tarefas!A:A,Tarefas!C:C) -> Programa de Melhorias | E5: Concluída | F5: Média | G5: Francisco Romulo de Aguiar;;;William Kennedy Rodrigues Lopes;Francisco Martins da Silva;Charliane Batista de Alencar | H5: Fernanda Sousa Araujo | I5: 2026-07-17 | J5: 2026-02-05 | M5: false | N5: 2026-07-17 | O5: Fernanda Sousa Araujo | P5: 0/6 | Q5: Rômulo ;Charliane;Martins;Kennedy;Douglas;Jennifer | T5: 755.5
A6: F1LFUkS0RUu3Ibi25ZzRWWQAJj2X | B6: Lançar melhoria do bimestre | C6: =_xlfn.XLOOKUP(A6,Tarefas!A:A,Tarefas!C:C) -> Programa de Melhorias | E6: Concluída | F6: Média | G6: Francisco Romulo de Aguiar;;;William Kennedy Rodrigues Lopes;Francisco Martins da Silva;Charliane Batista de Alencar | H6: Fernanda Sousa Araujo | I6: 2026-07-17 | J6: 2025-12-05 | M6: false | N6: 2026-07-17 | O6: Fernanda Sousa Araujo | P6: 0/6 | Q6: Rômulo ;Charliane;Martins;Kennedy;Douglas;Jennifer | T6: 349.29
A7: uQH-ZMJsr0CX1CPaui9Al2QAA1wN | B7: Lançar melhoria do bimestre | C7: =_xlfn.XLOOKUP(A7,Tarefas!A:A,Tarefas!C:C) -> Programa de Melhorias | E7: Concluída | F7: Média | G7: Francisco Romulo de Aguiar;;;William Kennedy Rodrigues Lopes;Francisco Martins da Silva;Charliane Batista de Alencar | H7: Fernanda Sousa Araujo | I7: 2026-07-17 | J7: 2025-10-05 | M7: false | N7: 2026-07-17 | O7: Fernanda Sousa Araujo | P7: 0/6 | Q7: Rômulo ;Charliane;Martins;Kennedy;Douglas;Jennifer | T7: 285
A8: txeRybaODEq_PH978neS1mQAGaS0 | B8: Lançar melhoria do bimestre | C8: =_xlfn.XLOOKUP(A8,Tarefas!A:A,Tarefas!C:C) -> Programa de Melhorias | E8: Concluída | F8: Média | G8: Francisco Romulo de Aguiar;;;William Kennedy Rodrigues Lopes;Francisco Martins da Silva;Charliane Batista de Alencar | H8: Fernanda Sousa Araujo | I8: 2026-07-17 | J8: 2025-08-08 | M8: false | N8: 2026-07-17 | O8: Fernanda Sousa Araujo | P8: 0/6 | Q8: Rômulo ;Charliane;Martins;Kennedy;Douglas;Jennifer | T8: 502.98
A9: tygljY6P00iU4kfls2vKV2QAG4Zo | B9: Lançar melhoria do bimestre | C9: =_xlfn.XLOOKUP(A9,Tarefas!A:A,Tarefas!C:C) -> Programa de Melhorias | E9: Concluída | F9: Média | G9: Francisco Romulo de Aguiar;;;William Kennedy Rodrigues Lopes;Francisco Martins da Silva;Charliane Batista de Alencar | H9: Fernanda Sousa Araujo | I9: 2026-07-17 | J9: 2024-12-05 | M9: false | N9: 2026-07-17 | O9: Fernanda Sousa Araujo | P9: 0/6 | Q9: Rômulo ;Charliane;Martins;Kennedy;Douglas;Jennifer | T9: 110.46
A10: 22BLBarPRUGDpRVdEMXK-WQAIPMG | B10: Lançar melhoria do bimestre | C10: =_xlfn.XLOOKUP(A10,Tarefas!A:A,Tarefas!C:C) -> Programa de Melhorias | E10: Concluída | F10: Média | G10: Francisco Romulo de Aguiar;;;William Kennedy Rodrigues Lopes;Francisco Martins da Silva;Charliane Batista de Alencar | H10: Fernanda Sousa Araujo | I10: 2024-07-05 | J10: 2024-10-31 | M10: false | N10: 2026-07-17 | O10: Fernanda Sousa Araujo | P10: 0/6 | Q10: Rômulo ;Charliane;Martins;Kennedy;Douglas;Jennifer | T10: 32.19
A11: XyQwFCHhokWxK8Qtp4qmkmQADVuN | B11: Fazer auditoria nos postos de trabalho dos lançamentos | C11: =_xlfn.XLOOKUP(A11,Tarefas!A:A,Tarefas!C:C) -> Tarefas Antigas | E11: Concluída | F11: Média | H11: Fernanda Sousa Araujo | I11: 2024-07-25 | J11: 2024-08-30 | M11: false | N11: 2024-09-05 | P11: 4/4 | Q11: Gerar laudo dos postos de trabalho e enviar para os envolvidos ;Registrar condições dos postos com fotos ;Analisar postos nos pilares de P5.0 e Ergonomia ;Passar nas linhas produtivas dos lançamentos | R11: Rotina | T11: 391.93
A12: Hl4x_KZhpkyOUlv5RxATVGQAM31J | B12: Criar as documentações do TEGAD dentro matrix | C12: =_xlfn.XLOOKUP(A12,Tarefas!A:A,Tarefas!C:C) -> Tarefas Antigas | E12: Concluída | F12: Média | H12: Fernanda Sousa Araujo | I12: 2024-07-25 | J12: 2024-08-02 | M12: false | N12: 2024-08-10 | T12: 52.13
A13: UjbIJMabvEC4WDGe9hiHvWQAK3Mj | B13: Criar as documentações dos montadores de layout dentro do matrix | C13: =_xlfn.XLOOKUP(A13,Tarefas!A:A,Tarefas!C:C) -> Tarefas Antigas | E13: Concluída | F13: Média | H13: Fernanda Sousa Araujo | I13: 2024-07-25 | J13: 2024-09-13 | M13: false | N13: 2026-07-17 | O13: Fernanda Sousa Araujo | T13: 173.06
A14: OxRSVcPgZEuV9LODx_vat2QAPkqZ | B14: Work sampling no processo de chamada ativa do PS7 | C14: =_xlfn.XLOOKUP(A14,Tarefas!A:A,Tarefas!C:C) -> Tarefas Antigas | E14: Concluída | F14: Média | G14: ; | H14: Fernanda Sousa Araujo | I14: 2024-07-25 | J14: 2024-08-23 | M14: false | N14: 2024-08-20 | P14: 4/4 | Q14: Gerar um gráfico com os dados de percurso com maior repetição ;Registrar os percursos realizados de movimentação dos operadores ;Acompanhar o processo ;Anotar as ocorrências ou divergências do processo | T14: 96.29
A15: kTIeuZuHKk6LutwStQOPmWQAKOcl | B15: Cadastro de pessoas treinadas aplicativo. | C15: =_xlfn.XLOOKUP(A15,Tarefas!A:A,Tarefas!C:C) -> Tarefas Antigas | E15: Concluída | F15: Média | G15: ; | I15: 2024-07-25 | J15: 2024-08-23 | M15: false | N15: 2024-08-20 | S15: Cadastrar listas de pessoas treinadas no aplicativo. | T15: 318.55
A16: HgnLevcgA0qC8e0NaziGdmQAAQrK | B16: Atualização planilhas SMED e criação de boletim. | C16: =_xlfn.XLOOKUP(A16,Tarefas!A:A,Tarefas!C:C) -> Tarefas Antigas | E16: Concluída | F16: Média | G16: ;William Kennedy Rodrigues Lopes | I16: 2024-08-12 | J16: 2024-08-23 | M16: false | N16: 2024-08-20 | T16: 0.98
A17: xZIuz0fqHEKGRIVvx_CjpGQAApIE | B17: Desenho | C17: =_xlfn.XLOOKUP(A17,Tarefas!A:A,Tarefas!C:C) -> Tarefas Antigas | E17: Concluída | F17: Média | I17: 2024-08-13 | J17: 2024-08-16 | M17: false | N17: 2024-08-13 | P17: 3/3 | Q17: Desenho da Mesa Posto de trabalho F3;Desenho do Layout F3-F4;Desenho do Layout Peças Técnicas | T17: 274.44
A18: lDsMV28xPka_W5yxSGhSB2QAJ3v7 | B18: Atualização planilha dos indicadores | C18: =_xlfn.XLOOKUP(A18,Tarefas!A:A,Tarefas!C:C) -> Tarefas Antigas | E18: Concluída | F18: Média | G18: ; | I18: 2024-08-20 | J18: 2024-08-21 | M18: false | N18: 2024-08-22 | T18: 210.98
A19: 8ZiKOBm8V0W1aszegn2HImQAO_b_ | B19: Atualizar checklist kaizen, ver com RH cadastro de pessoas treinadas em Kaizen. | C19: =_xlfn.XLOOKUP(A19,Tarefas!A:A,Tarefas!C:C) -> Tarefas Antigas | E19: Concluída | F19: Média | G19: ; | I19: 2024-08-20 | J19: 2024-08-21 | M19: false | N19: 2024-08-21 | T19: 389.75
A20: H1uUhGXRGU-77B3fs6q8LmQANBpP | B20: Organização materiais MEG | C20: =_xlfn.XLOOKUP(A20,Tarefas!A:A,Tarefas!C:C) -> Tarefas Antigas | E20: Concluída | F20: Média | G20: ; | I20: 2024-08-20 | J20: 2024-09-12 | M20: false | N20: 2026-07-17 | O20: Fernanda Sousa Araujo | T20: 499.61
A21: 1jM1QpSMA02fNwk_HDPi_mQAKDS8 | B21: Estudo Sala Impressão Digital | C21: =_xlfn.XLOOKUP(A21,Tarefas!A:A,Tarefas!C:C) -> Tarefas Antigas | E21: Concluída | F21: Média | I21: 2024-08-20 | J21: 2024-09-18 | M21: false | N21: 2026-07-17 | O21: Fernanda Sousa Araujo | T21: 612.74
A22: cQO-fezfA0eUz3P6IidJkGQABDk8 | B22: Organizar evento de melhorias | C22: =_xlfn.XLOOKUP(A22,Tarefas!A:A,Tarefas!C:C) -> Tarefas Antigas | E22: Concluída | F22: Média | H22: Fernanda Sousa Araujo | I22: 2024-09-27 | J22: 2024-09-24 | M22: false | N22: 2024-09-27 | O22: Fernanda Sousa Araujo | P22: 5/5 | Q22: Organizar o espaço de eventos ;Montar apresentação do evento ;Listar os dados dos premiados (Calçados e informações gerais);Levantar dados das avaliações de percepção. ;Treinar a apresentação | T22: 273.08
A23: SZ2NF2FBAE-UeRtXURXbLmQANNYa | B23: Passada Horizontal no TS6 | C23: =_xlfn.XLOOKUP(A23,Tarefas!A:A,Tarefas!C:C) -> Tarefas Antigas | E23: Concluída | F23: Média | H23: Fernanda Sousa Araujo | I23: 2024-09-27 | J23: 2024-09-27 | M23: false | N23: 2024-09-27 | O23: Fernanda Sousa Araujo | T23: 793.53
A24: DjnKbRcTlEar2AF5aYS1g2QAJm8W | B24: Passada Horizontal TS7 | C24: =_xlfn.XLOOKUP(A24,Tarefas!A:A,Tarefas!C:C) -> Tarefas Antigas | E24: Concluída | F24: Média | H24: Fernanda Sousa Araujo | I24: 2024-09-27 | J24: 2024-09-25 | M24: false | N24: 2024-09-27 | O24: Fernanda Sousa Araujo | T24: 987.87
A25: LQZZqn7VwUm8GsQfpC4GhGQADMSP | B25: MOI - Movimentadores de Caixas Montagem | C25: =_xlfn.XLOOKUP(A25,Tarefas!A:A,Tarefas!C:C) -> MOI, MOA, MODS | D25: Redução de 50 efetivos MOA, MOI e MODS | E25: Em andamento | F25: Importante | G25: Charliane Batista de Alencar | H25: Charliane Batista de Alencar | I25: 2026-07-17 | J25: 2026-07-24 | K25: 2026-07-06 | M25: true | P25: 6/8 | Q25: Validar com a gestão;Determinar padrões da operações;Testar nova proposta;Verificar possíveis propostas de melhorias ou automações;Avaliar durante uma semana dimensionamento pro fator X Padrão / aglutinado;Lançar FAP;Criar nova proposta de dimensionamento;Levantar situação atual | R25: Crato | T25: 74.97
A26: NkewH3A-5Eail--FODKxU2QAH1YF | B26: Otimização Setup Matriz EVA | C26: =_xlfn.XLOOKUP(A26,Tarefas!A:A,Tarefas!C:C) -> SMED | D26: Redução de 25% do tempo de setup de matriz e 15% setup de cor na injeção de EVA | E26: Não iniciado | F26: Média | G26: Francisco Romulo de Aguiar;Aliny Kelly De Assis Rufino | H26: Francisco Romulo de Aguiar | I26: 2026-07-17 | J26: 2026-08-31 | K26: 2026-07-20 | M26: false | P26: 5/9 | Q26: Acompanhar definição do carrinho compra ou confecção junto a fábrica;Análise de ganho para transformação das matrizes em troca rápida (Vagner).;Análise de setups Matriz. (20 à 24/07);Acompanhamento de implantação do Simon.;Teste de carrinho com capacidade para matrizes de entrada e saída.;Fazer analise do custo da estufa ligada o dia todo (Setups por maquina e por dia);Teste de pré aquecimento de matriz em setups reais.;Análise do fluxo de programação do EVA.;Montar material para reunião com Igor (sobre a estufa e moer purga) | T26: 426.94
A27: sNUu7Jc6NkyzqxvlG4HlcGQANkch | B27: Cerimônia de Premiação do Programa de Melhorias | C27: =_xlfn.XLOOKUP(A27,Tarefas!A:A,Tarefas!C:C) -> Programa de Melhorias | E27: Em andamento | F27: Média | G27: Leonardo Costa da Silva | H27: Leonardo Costa da Silva | I27: 2026-07-17 | J27: 2026-12-31 | M27: false | P27: 1/4 | Q27: Cerimônia de Premiação - Bimestre Set/Out 2026;Cerimônia de Premiação - Bimestre Jul/Ago 2026;Cerimônia de Premiação - Bimestre Mai/Jun 2026;Cerimônia de Premiação - Bimestre Nov/Dez 2026 | T27: 244.88
A28: Rs5Oc-Bkx02tuG9Y-sk0lGQAMxXl | B28: MOI - Auxiliar de Matrizaria | C28: =_xlfn.XLOOKUP(A28,Tarefas!A:A,Tarefas!C:C) -> MOI, MOA, MODS | D28: Redução de 50 efetivos MOA, MOI e MODS | E28: Em andamento | F28: Importante | G28: Charliane Batista de Alencar | H28: Charliane Batista de Alencar | I28: 2026-07-17 | J28: 2026-07-22 | K28: 2026-07-06 | M28: true | P28: 9/10 | Q28: Validar com a gestão;Tabulação de dados e classificação das atividades;Acompanhar turno B;Apresentar a gerência e coordenação;Verificar possíveis propostas de melhorias, transferências ou otimização de atividades;Colocar em teste para avaliar;Proposta de novo dimensionamento;Verificar com Kleilson a decisão de alterar dimensionamento, conforme avaliação no físico;Lançar FAP;Acompanhamento turno A (07/07 e 09/07) | R28: Crato | T28: 273.43
A29: t8_qJepIiUqnTdiC4yZkT2QAI7ze | B29: MOI - Matrizeiro | C29: =_xlfn.XLOOKUP(A29,Tarefas!A:A,Tarefas!C:C) -> MOI, MOA, MODS | D29: Redução de 50 efetivos MOA, MOI e MODS | E29: Não iniciado | F29: Importante | H29: Charliane Batista de Alencar | I29: 2026-07-17 | M29: false | P29: 0/8 | Q29: Tabulação de dados e classificação das atividades;Proposta de novo dimensionamento;Colocar em teste para avaliar;Validar com a gestão;Acompanhamento turno A;Acompanhar turno B;Lançar FAP;Verificar possíveis propostas de melhorias, transferências ou otimização de atividades | R29: Crato | T29: 719.5
A30: XD1eWNDN_ECyHQuAr9pQImQAJevi | B30: SMED Setup de Cor EVA | C30: =_xlfn.XLOOKUP(A30,Tarefas!A:A,Tarefas!C:C) -> SMED | D30: Redução de 25% do tempo de setup de matriz e 15% setup de cor na injeção de EVA | E30: Não iniciado | F30: Média | G30: Francisco Romulo de Aguiar;Aliny Kelly De Assis Rufino | H30: Francisco Romulo de Aguiar | I30: 2026-07-17 | J30: 2026-10-31 | M30: false | P30: 5/7 | Q30: Análise da troca de cor sem a utilização do material de limpeza.;Análise ECRS - Troca de cor simples e complexa;Análise de tempo perdido com expurgo, recorte e recolhimento da purga.;Proposta de alterações para redução de material expurgado (Reduzir material dentro do injetor).;Realizar teste no mini moinho com a purga do EVA para ver o comportamento do material.;Criar mapa de raciocínio da troca de cor;Levantamento de ganhos. | T30: 732.63
A31: DoKMHOwn7UCOR_vLrOHv3mQAHbad | B31: MOI - Tegad / Célula de Layout | C31: =_xlfn.XLOOKUP(A31,Tarefas!A:A,Tarefas!C:C) -> MOI, MOA, MODS | D31: Redução de 50 efetivos MOA, MOI e MODS | E31: Em andamento | F31: Importante | G31: William Kennedy Rodrigues Lopes;Charliane Batista de Alencar | H31: Charliane Batista de Alencar | I31: 2026-07-17 | K31: 2026-07-13 | M31: false | P31: 4/7 | Q31: Levantamento da situação atual;Apresentar e validar com a gestão;Mapear todas as atividades realizadas na área e funções;Lançar FAP;Testar nova proposta de dimensionamento;Verificar possíveis melhorias ou automações de processos;Nova proposta de dimensionamento | S31: Link Apresentação: https://canva.link/h3vnpu6cgzovy20 | T31: 451.23
A32: HXKuxw-cBUepbRalBZSt1mQAKYct | B32: Credenciamento - Programa de Melhorias | C32: =_xlfn.XLOOKUP(A32,Tarefas!A:A,Tarefas!C:C) -> Programa de Melhorias | D32: Atingir 85% de aderência no Programa de Melhorias | E32: Concluída | F32: Média | G32: Leonardo Costa da Silva | H32: Leonardo Costa da Silva | I32: 2026-07-17 | J32: 2026-07-22 | M32: false | N32: 2026-07-24 | O32: Leonardo Costa da Silva | P32: 2/2 | Q32: Reunião para montagem do Plano de Credenciamento do Programa de Melhorias;Estruturar o conteúdo de Treinamento para o Público de Preparadores ate Supervisão | S32: Foi criado o Manual com o objetivo de conduzir o conteudo para TReinamento para o Publico, abordando sobre o programa de Melhorias, o seu funcionamento, bem como, o planejamento da cerimônia de premiação. | T32: 475.39
A33: V0yIkFtIWEOskxThXpxkY2QAM3ON | B33: Padronização das Embalagens | C33: =_xlfn.XLOOKUP(A33,Tarefas!A:A,Tarefas!C:C) -> Padronizações/Certificações | E33: Não iniciado | F33: Média | G33: Leonardo Costa da Silva | H33: Leonardo Costa da Silva | I33: 2026-07-17 | J33: 2026-08-31 | M33: false | P33: 0/4 | Q33: Mobiliários - Crato;Mobiliarios - Fortaleza;Criação do material de apresentação da Hora da Excelência - Padronização das Embalagens;Mobiliários - Sobral | T33: 396.3
A34: CX98n3yEK0mDhVfC_Fi1J2QAHMG- | B34: Padronização das Salas de Tintas | C34: =_xlfn.XLOOKUP(A34,Tarefas!A:A,Tarefas!C:C) -> Padronizações/Certificações | E34: Não iniciado | F34: Média | H34: Leonardo Costa da Silva | I34: 2026-07-17 | M34: false | T34: 102.4
A35: hiwXVtGDc0-i01bBHDNL72QANeXx | B35: Padronização do Tingimento | C35: =_xlfn.XLOOKUP(A35,Tarefas!A:A,Tarefas!C:C) -> Padronizações/Certificações | E35: Não iniciado | F35: Média | H35: Leonardo Costa da Silva | I35: 2026-07-17 | M35: false | T35: 960.52
A36: ZdZflJXSmkK-wVFOke3F5GQAP5-z | B36: [Semana 27-31/07] Automação de atividades de Organização do Programa de Melhorias | C36: =_xlfn.XLOOKUP(A36,Tarefas!A:A,Tarefas!C:C) -> Programa de Melhorias | E36: Em andamento | F36: Média | G36: Thiago Roberto Andrade Aguiar | H36: Leonardo Costa da Silva | I36: 2026-07-17 | J36: 2026-07-31 | M36: true | P36: 1/5 | Q36: Automatizar montagem da apresentação do Programa de Melhorias;Analise dos arquivos e dos fluxos para viabilizar automação;Automatizar montagem dos Certificados;Automatizar Convite dos Premiados e Convite Oficial para Gerencias do Programa de Melhorias;Criação dos arquivos do material de planejamento em pasta para automação | T36: 503.93
A37: Yvny0_yZ00u0pFkafmUt9mQAFqat | B37: Criar operação de aplicar rolinho curvado logo pequeno | C37: =_xlfn.XLOOKUP(A37,Tarefas!A:A,Tarefas!C:C) -> MTM/Impressão 3D | E37: Concluída | F37: Média | G37: Leonardo Galdino de Oliveira | H37: Leonardo Galdino de Oliveira | I37: 2026-07-17 | J37: 2026-07-24 | K37: 2026-07-20 | M37: false | N37: 2026-07-30 | O37: Leonardo Galdino de Oliveira | T37: 618.85
A38: zuLDstg9b0efs3su_Ph4fGQAIxsY | B38: Montar apresentação para treinamento novo dosador | C38: =_xlfn.XLOOKUP(A38,Tarefas!A:A,Tarefas!C:C) -> Padronizações/Certificações | E38: Não iniciado | F38: Média | G38: Leonardo Galdino de Oliveira | H38: Leonardo Galdino de Oliveira | I38: 2026-07-17 | J38: 2026-07-24 | K38: 2026-07-20 | M38: true | T38: 194.13
A39: VielfIXtXEiR6oY1QY6E5GQABVwj | B39: [Semana 20-24/07] Criação dos Famílias - Serigrafia Fábrica 05 | C39: =_xlfn.XLOOKUP(A39,Tarefas!A:A,Tarefas!C:C) -> RPA | E39: Concluída | F39: Urgente | G39: Nalbert de Matos Vieira | H39: Nalbert de Matos Vieira | I39: 2026-07-17 | J39: 2026-07-24 | K39: 2026-07-01 | M39: false | N39: 2026-07-23 | O39: Nalbert de Matos Vieira | P39: 5/5 | Q39: Levantar dados de processo de Serigrafia da Fábrica 05;Criar bases de famílias e gráficos para visualização da distribuição das Famílias;Analisar os padrões p/lacas/hr dos modelos para criar os ranges das Famílias;Levantar dados de PQP;Analisar os padrões pares/hr dos modelos para criar os ranges das Famílias | T39: 505.12
A40: qDcgfgf80kykqSwwa8PPaWQAFFo8 | B40: Projeto TR Cabine de Pintura Manual | C40: =_xlfn.XLOOKUP(A40,Tarefas!A:A,Tarefas!C:C) -> SMED | D40: Redução de 50 efetivos MOA, MOI e MODS | E40: Em andamento | F40: Importante | G40: Francisco Romulo de Aguiar | I40: 2026-07-18 | J40: 2026-08-31 | M40: false | P40: 0/3 | Q40: Confecção de bombas TS7 (nec. 32/ feito 18);Replicação para TS6 (nec. 26);Replicação para TS1 (nec. 12) | T40: 107.76
A41: PsqUFHQh2EmWCDzylxrMEWQAMyNp | B41: Enviar boletim de Aderência de Melhorias - Quinzenal para Gerentes e Coordenadores | C41: =_xlfn.XLOOKUP(A41,Tarefas!A:A,Tarefas!C:C) -> Programa de Melhorias | E41: Não iniciado | F41: Média | G41: Leonardo Costa da Silva | H41: Leonardo Costa da Silva | I41: 2026-07-18 | J41: 2026-12-31 | K41: 2026-08-01 | M41: false | S41: Adicionar informações relacionadas ao Programa de Melhorias - Aderencia de Melhorias, Aderencia das Ideias do QRCode, Visão geral das gerencias e o impacto financeiro. | T41: 87.21
A42: hz469tm0u0-84IeJuXfluGQAIrdx | B42: Enviar boletim semanal relacionado a Gestão de Melhorias da área do Tiago - Engenharia | C42: =_xlfn.XLOOKUP(A42,Tarefas!A:A,Tarefas!C:C) -> Programa de Melhorias | E42: Não iniciado | F42: Média | G42: Leonardo Costa da Silva | H42: Fernanda Sousa Araujo | I42: 2026-08-14 | J42: 2026-08-18 | K42: 2026-08-13 | M42: false | T42: 511.17
A43: 08E3NE5cTEq1sd_TzjrEVWQALWnl | B43: Enviar boletim semanal relacionado a Gestão de Melhorias da área do Tiago - Engenharia | C43: =_xlfn.XLOOKUP(A43,Tarefas!A:A,Tarefas!C:C) -> Programa de Melhorias | E43: Concluída | F43: Média | G43: Leonardo Costa da Silva | H43: Fernanda Sousa Araujo | I43: 2026-08-14 | J43: 2026-08-11 | K43: 2026-08-06 | M43: false | N43: 2026-08-14 | O43: Fernanda Sousa Araujo | T43: 939.14
A44: vyEptvuaskOXeZr0cHELf2QAETqG | B44: Enviar boletim semanal relacionado a Gestão de Melhorias da área do Tiago - Engenharia | C44: =_xlfn.XLOOKUP(A44,Tarefas!A:A,Tarefas!C:C) -> Programa de Melhorias | E44: Concluída | F44: Média | G44: Leonardo Costa da Silva | H44: Leonardo Costa da Silva | I44: 2026-07-23 | J44: 2026-08-06 | K44: 2026-08-01 | M44: false | N44: 2026-08-14 | O44: Fernanda Sousa Araujo | T44: 204.8
A45: ezE1p0UcT0yNxkv7BuF1a2QAKUsr | B45: Enviar boletim semanal relacionado a Gestão de Melhorias da área do Tiago - Engenharia | C45: =_xlfn.XLOOKUP(A45,Tarefas!A:A,Tarefas!C:C) -> Programa de Melhorias | E45: Concluída | F45: Média | G45: Leonardo Costa da Silva | H45: Leonardo Costa da Silva | I45: 2026-07-18 | J45: 2026-07-21 | K45: 2026-07-17 | M45: false | N45: 2026-07-22 | O45: Leonardo Costa da Silva | T45: 805.18
A46: tS3ynbJ2PUmw2ahAWkxC3WQAGf5h | B46: Criar operação de montar enfeite com novo equipamento | C46: =_xlfn.XLOOKUP(A46,Tarefas!A:A,Tarefas!C:C) -> MTM/Impressão 3D | E46: Concluída | F46: Média | G46: Leonardo Galdino de Oliveira | H46: Leonardo Galdino de Oliveira | I46: 2026-07-18 | J46: 2026-07-24 | K46: 2026-07-20 | M46: false | N46: 2026-07-30 | O46: Leonardo Galdino de Oliveira | T46: 100.58
A47: CuZgcze8_UKVNKhnXWgm1WQAN6E8 | B47: Acompanhar entrega dos móveis embalagem | C47: =_xlfn.XLOOKUP(A47,Tarefas!A:A,Tarefas!C:C) -> Padronizações/Certificações | E47: Não iniciado | F47: Média | G47: Leonardo Galdino de Oliveira | H47: Leonardo Galdino de Oliveira | I47: 2026-07-18 | J47: 2026-12-31 | K47: 2026-07-20 | M47: false | T47: 588.3
A48: IcdR8JEto02P-PM5dTzhGmQALFKt | B48: Acompanhar entrega das bombas duplas | C48: =_xlfn.XLOOKUP(A48,Tarefas!A:A,Tarefas!C:C) -> Padronizações/Certificações | E48: Não iniciado | F48: Média | G48: Leonardo Galdino de Oliveira | H48: Leonardo Galdino de Oliveira | I48: 2026-07-18 | J48: 2026-08-28 | K48: 2026-07-20 | M48: false | P48: 0/5 | Q48: F1 - Total - 12, entregue - 7;F7 - Total - 38, entregue - 21;Previsão de entrega 28/08/2026;F6 - Total - 26, entregue - 6;33 bombas entregues Atualização - 14/08/2026 | T48: 535.16
A49: 0vsw8n4Q7Ei7dKijGz-ZuGQAJRQY | B49: Projeto 02 - Dimensionamento dos Trocadores de Layout Fáb. 06 | C49: =_xlfn.XLOOKUP(A49,Tarefas!A:A,Tarefas!C:C) -> MOI, MOA, MODS | D49: Redução de 50 efetivos MOA, MOI e MODS | E49: Não iniciado | F49: Média | G49: William Kennedy Rodrigues Lopes | H49: William Kennedy Rodrigues Lopes | I49: 2026-07-18 | J49: 2026-08-14 | M49: true | P49: 3/4 | Q49: Acompanhar físico x tabela de cálculo.;Criar tabela de dimensionamento da F06;Validar processo de dimensionamento hora a hora.;Testar processo de automação das informações | T49: 432.77
A50: 3kqVaLHdgUuM5WHpeu2VF2QAPOok | B50: Fazer análise de ganhos dos modelos com elevador | C50: =_xlfn.XLOOKUP(A50,Tarefas!A:A,Tarefas!C:C) -> MTM/Impressão 3D | E50: Concluída | F50: Média | G50: Leonardo Galdino de Oliveira | H50: Leonardo Galdino de Oliveira | I50: 2026-07-18 | J50: 2026-07-21 | K50: 2026-07-20 | M50: false | N50: 2026-07-23 | O50: Leonardo Galdino de Oliveira | T50: 463.31
A51: EdGjdxfvPke8i4ykf3f3Y2QAEcAO | B51: Atualização dos ganhos dos robôs de pintura | C51: =_xlfn.XLOOKUP(A51,Tarefas!A:A,Tarefas!C:C) -> Padronizações/Certificações | E51: Em andamento | F51: Importante | G51: Leonardo Galdino de Oliveira | H51: Leonardo Galdino de Oliveira | I51: 2026-07-20 | J51: 2026-12-31 | K51: 2026-07-20 | M51: false | T51: 438.74
A52: Yo4Dt-bPr06xy8GLKPU6mWQAC7So | B52: Projeto 02 - Dimensionamento dos Trocadores de Layout Fáb. 07 | C52: =_xlfn.XLOOKUP(A52,Tarefas!A:A,Tarefas!C:C) -> MOI, MOA, MODS | D52: Redução de 50 efetivos MOA, MOI e MODS | E52: Não iniciado | F52: Média | H52: Fernanda Sousa Araujo | I52: 2026-07-20 | M52: false | P52: 0/4 | Q52: Testar processo de automação das informações;Criar tabela de dimensionamento;Acompanhar físico x tabela de cálculo.;Validar processo de dimensionamento hora a hora. | T52: 815.71
A53: -xACx8adIU6pxoiKRb2o52QAAkJJ | B53: Projeto 02 - Dimensionamento dos Trocadores de Layout Crato | C53: =_xlfn.XLOOKUP(A53,Tarefas!A:A,Tarefas!C:C) -> MOI, MOA, MODS | D53: Redução de 50 efetivos MOA, MOI e MODS | E53: Não iniciado | F53: Média | G53: William Kennedy Rodrigues Lopes | H53: Fernanda Sousa Araujo | I53: 2026-07-20 | M53: false | P53: 0/4 | Q53: Testar processo de automação das informações;Criar tabela de dimensionamento;Acompanhar físico x tabela de cálculo.;Validar processo de dimensionamento hora a hora. | T53: 312.45
A54: S92B9tmFzkGOmEApomfXDmQAGULD | B54: Projeto 02 - Dimensionamento dos Trocadores de Layout Fáb. 01 | C54: =_xlfn.XLOOKUP(A54,Tarefas!A:A,Tarefas!C:C) -> MOI, MOA, MODS | D54: Redução de 50 efetivos MOA, MOI e MODS | E54: Não iniciado | F54: Média | G54: William Kennedy Rodrigues Lopes | H54: Fernanda Sousa Araujo | I54: 2026-07-20 | M54: false | P54: 0/4 | Q54: Testar processo de automação das informações;Validar processo de dimensionamento hora a hora.;Criar tabela de dimensionamento;Acompanhar físico x tabela de cálculo. | T54: 45.21
A55: o96uDVPn7kO1BO1Et1ngDWQADbuj | B55: Projeto 01 - Dimensionamento dos Reguladores de Telas | C55: =_xlfn.XLOOKUP(A55,Tarefas!A:A,Tarefas!C:C) -> MOI, MOA, MODS | D55: Redução de 50 efetivos MOA, MOI e MODS | E55: Concluída | F55: Média | G55: William Kennedy Rodrigues Lopes | H55: Fernanda Sousa Araujo | I55: 2026-07-20 | J55: 2026-07-31 | M55: false | N55: 2026-07-20 | O55: Fernanda Sousa Araujo | P55: 5/5 | Q55: Criar tabela de cálculo do dimensionamento;Adequar e validar o quadro de acordo com a demanda.;Aplicar automação de processo da tabela de cálculo;Acompanhar físico x Tabela de cálculo;Lançar FAP | T55: 50.34
A56: ZoTDwBVfnEmPgFXlKmTqjWQACeHJ | B56: Levantamento das atividades de assistentes | C56: =_xlfn.XLOOKUP(A56,Tarefas!A:A,Tarefas!C:C) -> RPA | E56: Concluída | F56: Média | G56: Thiago Roberto Andrade Aguiar | H56: Thiago Roberto Andrade Aguiar | I56: 2026-07-21 | J56: 2026-07-17 | M56: false | N56: 2026-08-14 | O56: Leonardo Costa da Silva | P56: 5/5 | Q56: Atividades Expandido/EVA;Atividades F3;Atividades TS;Levantamento das atividades automatizadas;Atividades F5 | T56: 536.25
A57: BviPoBNEQkqKe9OduuH0yGQABFvA | B57: BI - Dados de Try out | C57: =_xlfn.XLOOKUP(A57,Tarefas!A:A,Tarefas!C:C) -> RPA | E57: Concluída | F57: Média | G57: Thiago Roberto Andrade Aguiar | H57: Thiago Roberto Andrade Aguiar | I57: 2026-07-21 | J57: 2026-07-17 | M57: false | N57: 2026-07-23 | O57: Thiago Roberto Andrade Aguiar | T57: 904.74
A58: LanAVr4K706TZ6Q0KnKk12QAOVHp | B58: Atualização Automação Robô de Pintura | C58: =_xlfn.XLOOKUP(A58,Tarefas!A:A,Tarefas!C:C) -> RPA | E58: Não iniciado | F58: Baixa | G58: Thiago Roberto Andrade Aguiar | H58: Thiago Roberto Andrade Aguiar | I58: 2026-07-21 | J58: 2026-07-17 | M58: true | S58: Devido a prioridade da revisão do indicador de aproveitamento de estrutura não foi possível concluir a atividade. | T58: 695.57
A59: -WOhHxUVG0uivvr_8oCQf2QANUxA | B59: Indicadores Internos Engenharia | C59: =_xlfn.XLOOKUP(A59,Tarefas!A:A,Tarefas!C:C) -> RPA | E59: Concluída | F59: Média | G59: Thiago Roberto Andrade Aguiar;Leonardo Costa da Silva | H59: Thiago Roberto Andrade Aguiar | I59: 2026-07-21 | J59: 2026-07-30 | M59: false | N59: 2026-07-31 | O59: Thiago Roberto Andrade Aguiar | P59: 5/5 | Q59: Certificado;Apresentação;Projetos de Engenharia;Requisitar calçados;Kahoot | T59: 379.62
A60: 2rd8eeiMKk-jy8_LpN3712QAFQiE | B60: Replicação - Automação de download de documentação Matrix | C60: =_xlfn.XLOOKUP(A60,Tarefas!A:A,Tarefas!C:C) -> RPA | E60: Em andamento | F60: Média | G60: Thiago Roberto Andrade Aguiar | H60: Thiago Roberto Andrade Aguiar | I60: 2026-07-21 | J60: 2026-07-17 | M60: true | P60: 2/3 | Q60: Realizar teste em escala;Realizar teste piloto;Ajustar código | S60: Replicar automação de download para salvar arquivos para a produção | T60: 290.77
A61: f33MEiU6ukyy7jcLOTwn8GQAAeql | B61: Fechar com fábrica envio dos armários sem gaveta | C61: =_xlfn.XLOOKUP(A61,Tarefas!A:A,Tarefas!C:C) -> Padronizações/Certificações | E61: Concluída | F61: Importante | G61: Leonardo Galdino de Oliveira | H61: Leonardo Galdino de Oliveira | I61: 2026-07-22 | J61: 2026-07-24 | K61: 2026-07-20 | M61: false | N61: 2026-07-23 | O61: Leonardo Galdino de Oliveira | T61: 917.2
A62: 9zblwr9fLE-QywwtpFEvcWQAKiRz | B62: Enviar caixas de celular para unidade de Crato | C62: =_xlfn.XLOOKUP(A62,Tarefas!A:A,Tarefas!C:C) -> Padronizações/Certificações | E62: Concluída | F62: Importante | H62: Leonardo Galdino de Oliveira | I62: 2026-07-22 | J62: 2026-07-24 | K62: 2026-07-20 | M62: false | N62: 2026-07-23 | O62: Fernanda Sousa Araujo | T62: 465.7
A63: KONvmT0RqUW8D3ZOUnzvNGQAM043 | B63: Montar apresentação sobre o posto de revisão | C63: =_xlfn.XLOOKUP(A63,Tarefas!A:A,Tarefas!C:C) -> MTM/Impressão 3D | E63: Concluída | F63: Média | G63: Leonardo Galdino de Oliveira | H63: Leonardo Galdino de Oliveira | I63: 2026-07-23 | J63: 2026-07-27 | K63: 2026-07-23 | M63: false | N63: 2026-08-14 | O63: Fernanda Sousa Araujo | T63: 936.21
A64: 2K7dMYi9JEystw4Nj-ykz2QAF_H4 | B64: Criar operação Montar 2 comp. no gabarito sapata | C64: =_xlfn.XLOOKUP(A64,Tarefas!A:A,Tarefas!C:C) -> MTM/Impressão 3D | E64: Concluída | F64: Média | G64: Leonardo Galdino de Oliveira | H64: Leonardo Galdino de Oliveira | I64: 2026-07-23 | J64: 2026-07-24 | K64: 2026-07-20 | M64: false | N64: 2026-07-23 | O64: Leonardo Galdino de Oliveira | T64: 456.62
A65: 0HISTDzjREupuKEUBXomwWQAHRPX | B65: [Semana 27-31/07] Melhorias - Semanal F03 | C65: =_xlfn.XLOOKUP(A65,Tarefas!A:A,Tarefas!C:C) -> RPA | E65: Concluída | F65: Média | G65: Nalbert de Matos Vieira | H65: Nalbert de Matos Vieira | I65: 2026-07-23 | J65: 2026-07-31 | K65: 2026-07-23 | M65: false | N65: 2026-07-31 | O65: Nalbert de Matos Vieira | P65: 3/3 | Q65: Adicionar dados pendentes;Revisão base para os dados de Volume;Adequar as novas colunas | T65: 879.46
A66: H3MlmWZ1QEyUZOuOMyiq92QANZ5- | B66: Estudo sobre setup de cor na rotografia | C66: =_xlfn.XLOOKUP(A66,Tarefas!A:A,Tarefas!C:C) -> SMED | E66: Concluída | F66: Importante | I66: 2026-07-23 | J66: 2026-07-31 | K66: 2026-07-27 | M66: false | N66: 2026-08-03 | P66: 4/4 | Q66: Gravar vídeos de trocas de cor simples e complexas na rotografia;Escolher um produto para fazer análise da carga pendente;Fazer simulação da perda de tempo e custo do setup de acordo com a carga;Analisar possibilidade de fazer melhor sequenciamento de cores. | T66: 75.99
A67: CVrvPxUjU06TmKhbZjcXwmQAC0dR | B67: [Semana 20-24/07] Robô de alteração de Processos | C67: =_xlfn.XLOOKUP(A67,Tarefas!A:A,Tarefas!C:C) -> RPA | E67: Concluída | F67: Média | G67: Nalbert de Matos Vieira | H67: Nalbert de Matos Vieira | I67: 2026-07-23 | J67: 2026-07-24 | M67: false | N67: 2026-07-31 | O67: Nalbert de Matos Vieira | P67: 4/4 | Q67: Mapear atividade de alteração do processo e operações de Base Coating;Criar robô para alteração automatizada;Testes e Revisões no robô;Execução da lista de componentes para alteração | T67: 646.13
A68: uOQd15wA7ku_i9V9PqU_FmQAPAh8 | B68: Definição de Padrão (Capacidade) das esteiras do CD. | C68: =_xlfn.XLOOKUP(A68,Tarefas!A:A,Tarefas!C:C) -> Logística | E68: Concluída | F68: Média | G68: Francisco Martins da Silva | H68: Fernanda Sousa Araujo | I68: 2026-07-23 | J68: 2026-07-24 | M68: false | N68: 2026-07-23 | O68: Fernanda Sousa Araujo | T68: 23.01
A69: zTEdatnkPUWYyj2qrOs7WWQAF7FB | B69: Análise de layout das salas de tintas para recebimento dos contêiner de adesivo. | C69: =_xlfn.XLOOKUP(A69,Tarefas!A:A,Tarefas!C:C) -> Logística | E69: Concluída | F69: Média | G69: Francisco Martins da Silva | H69: Fernanda Sousa Araujo | I69: 2026-07-23 | M69: false | N69: 2026-07-23 | O69: Fernanda Sousa Araujo | T69: 315.31
A70: YaEnYWINY0iGZiTRFh-SgWQAIjcR | B70: Plano de comunicação do Programa de Melhorias - Gerencias e Coordenadores | C70: =_xlfn.XLOOKUP(A70,Tarefas!A:A,Tarefas!C:C) -> Programa de Melhorias | E70: Não iniciado | F70: Média | G70: Leonardo Costa da Silva | H70: Leonardo Costa da Silva | I70: 2026-07-23 | J70: 2026-08-15 | K70: 2026-08-10 | M70: false | P70: 2/2 | Q70: Estruturar material e criar o plano de comunicação para Gerentes e Coordenadores;Cronograma de Apresentação do Material - Programa de Melhorias - Conteúdo e Aderência | T70: 947.2
A71: A8URaDb6EESh35VGQ1yc5mQABR88 | B71: Estudo - Setup de Cor | C71: =_xlfn.XLOOKUP(A71,Tarefas!A:A,Tarefas!C:C) -> SMED | E71: Em andamento | F71: Média | G71: Daniel Viana de Carvalho | H71: Daniel Viana de Carvalho | I71: 2026-07-23 | J71: 2026-08-07 | M71: true | P71: 5/5 | Q71: Levantar quantidade de PP/Líder Técnico por turno;Criar mapa de raciocínio do setup de cor para investigar as causas do acumulo de tempo;Verificar quantidade de setups simples e complexos por turno;Analisar os resultado dos tempos de Setup de Cor (estratificado);Acompanhar setups de cor | T71: 522.23
A72: iUqxskDAfk2VERuMOQ5KiGQAEbH8 | B72: Criação do Video do Evento do Programa de Melhorias | C72: =_xlfn.XLOOKUP(A72,Tarefas!A:A,Tarefas!C:C) -> Programa de Melhorias | E72: Concluída | F72: Importante | G72: Leonardo Costa da Silva | H72: Leonardo Costa da Silva | I72: 2026-07-23 | J72: 2026-07-31 | K72: 2026-07-27 | M72: false | N72: 2026-07-31 | O72: Leonardo Costa da Silva | P72: 0/1 | Q72: Finalizar edição do vídeo do Evento de Melhorias | T72: 627.75
A73: 9qD0NlOdtE6VRfIRsssna2QAAHId | B73: Criar cronograma de Passadas com Supervisores da Engenharia - Manoel | C73: =_xlfn.XLOOKUP(A73,Tarefas!A:A,Tarefas!C:C) -> RPA | E73: Concluída | F73: Importante | G73: Leonardo Costa da Silva | H73: Leonardo Costa da Silva | I73: 2026-07-23 | J73: 2026-07-31 | K73: 2026-07-27 | M73: false | N73: 2026-08-06 | O73: Leonardo Costa da Silva | T73: 8.67
A74: Ia8IBp08ZEygk65zYtgGS2QACnKh | B74: Análise Engate de Escoamento (Dosador) | C74: =_xlfn.XLOOKUP(A74,Tarefas!A:A,Tarefas!C:C) -> SMED | E74: Em andamento | F74: Média | G74: Daniel Viana de Carvalho | H74: Daniel Viana de Carvalho | I74: 2026-07-23 | J74: 2026-07-31 | M74: true | P74: 0/4 | Q74: Caso necessário, estudar novo protótipo para substituir o atual;Analisar modificação do protótipo atual;Pensar novo método para evitar descer da máquina com peso (matéria prima em excesso);Readequação do engate atual | T74: 502.3
A75: eRjP6tBFjkGUNrZ_bgTDPWQAEMX9 | B75: Estruturar com as áreas sobre a Embalagem para o momento da Hora da Excelência | C75: =_xlfn.XLOOKUP(A75,Tarefas!A:A,Tarefas!C:C) -> Padronizações/Certificações | E75: Não iniciado | F75: Média | G75: Leonardo Costa da Silva | H75: Leonardo Costa da Silva | I75: 2026-07-23 | J75: 2026-08-15 | K75: 2026-07-27 | M75: false | T75: 127.34
A76: aakzS-Auz0iP8i-K-YluAmQAFq5E | B76: 22/07 - Reunião de Indicadores dos Montadores | C76: =_xlfn.XLOOKUP(A76,Tarefas!A:A,Tarefas!C:C) -> Pendências Fechamento de Indicadores | E76: Não iniciado | F76: Média | H76: Fernanda Sousa Araujo | I76: 2026-07-23 | J76: 2026-08-07 | M76: true | P76: 0/1 | Q76: Cronograma dos vídeos do Programa de Melhorias | T76: 280.72
A77: YuFczN61RUKxveXsNdFoa2QABRdG | B77: 16/07 - Fechamento de Indicadores dos Transformadores | C77: =_xlfn.XLOOKUP(A77,Tarefas!A:A,Tarefas!C:C) -> Pendências Fechamento de Indicadores | E77: Não iniciado | F77: Média | H77: Fernanda Sousa Araujo | I77: 2026-07-23 | J77: 2026-08-07 | M77: true | P77: 0/6 | Q77: Analisar complexidade da injeção de Fortaleza comparando com Sobral, resultados de OPE.;Comparativo de ineficiência da injeção full com expandido;Acompanhar implantação do SIMON na injeção de EVA;Apresentar quantidade de melhorias do grupo de inelegíveis;Separar os produtos com matrizes novas nos blocos das ineficiências.;Analisar ajuste de meta da injeção de Crato | T77: 52.23
A78: nfOLeiVx7EGZbEB9egTTjGQAGoDc | B78: Abertura de Solicitação de licença para IA - Para criação de vídeos HeyGEn | C78: =_xlfn.XLOOKUP(A78,Tarefas!A:A,Tarefas!C:C) -> Programa de Melhorias | E78: Concluída | F78: Média | G78: Leonardo Costa da Silva | H78: Leonardo Costa da Silva | I78: 2026-07-24 | J78: 2026-07-23 | K78: 2026-07-23 | M78: false | N78: 2026-07-24 | O78: Leonardo Costa da Silva | S78: Foi solicitado ao Renan Grabo o levantamento das IA com o objetivo de criação de vídeos e o mesmo realizou o levantamento. Valor | T78: 976.11
A79: Gq17wQxRgESknNCzCUcW8WQABvJb | B79: AMR para entrega de insumos (Sala de Tintas) | C79: =_xlfn.XLOOKUP(A79,Tarefas!A:A,Tarefas!C:C) -> MOI, MOA, MODS | E79: Não iniciado | F79: Média | H79: Charliane Batista de Alencar | I79: 2026-07-25 | M79: false | T79: 426.08
A80: bYSBzwl280uSIRXISLKFq2QAEy0t | B80: POP da troca de número na rotografia friso | C80: =_xlfn.XLOOKUP(A80,Tarefas!A:A,Tarefas!C:C) -> SMED | E80: Concluída | F80: Média | I80: 2026-07-28 | J80: 2026-07-28 | M80: false | N80: 2026-07-28 | T80: 499.33
A81: 26dsmOCXAEeQi41emCT2ZmQAGXzw | B81: Estudos - Sala de Amostras | C81: =_xlfn.XLOOKUP(A81,Tarefas!A:A,Tarefas!C:C) -> SMED | E81: Em andamento | F81: Importante | G81: Daniel Viana de Carvalho;Aliny Kelly De Assis Rufino | H81: Daniel Viana de Carvalho | I81: 2026-07-29 | J81: 2026-08-21 | K81: 2026-07-21 | M81: false | P81: 7/8 | Q81: Implementar pastas nas máquinas;Acompanhamento: pastas sendo utilizadas no novo formato (Acompanhar no físico);Aprofundamento na análise do histórico de solicitações dos kits (Solicitação André);Definir quantidade de pastas necessárias para compra;Análise do histórico de solicitações de kits;Protótipo de layout;Medição Sala de revisão x Sala de amostra;Implementação: realocação de pastas com divisórias | T81: 705.43
A82: o7wTpgviUkibX92RQKooLWQAOo1A | B82: Fazer análise da troca de caixa preparação com elevador | C82: =_xlfn.XLOOKUP(A82,Tarefas!A:A,Tarefas!C:C) -> MTM/Impressão 3D | E82: Concluída | F82: Média | G82: Leonardo Galdino de Oliveira | H82: Leonardo Galdino de Oliveira | I82: 2026-07-30 | J82: 2026-07-31 | K82: 2026-07-27 | M82: false | N82: 2026-07-31 | O82: Fernanda Sousa Araujo | T82: 204.85
A83: 9BsFcrppZ0GNy5dAH1A8wGQAMbUC | B83: Fazer análise do apontamento SIMON Setup | C83: =_xlfn.XLOOKUP(A83,Tarefas!A:A,Tarefas!C:C) -> MTM/Impressão 3D | E83: Concluída | F83: Média | G83: Leonardo Galdino de Oliveira | H83: Leonardo Galdino de Oliveira | I83: 2026-07-30 | J83: 2026-07-31 | K83: 2026-07-27 | M83: false | N83: 2026-07-31 | O83: Fernanda Sousa Araujo | T83: 592.49
A84: OR3EECFgIUGH8MdHCrB-rGQAE-F1 | B84: Fazer análise apontamento SIMON Disponibilidade | C84: =_xlfn.XLOOKUP(A84,Tarefas!A:A,Tarefas!C:C) -> MTM/Impressão 3D | E84: Concluída | F84: Média | G84: Leonardo Galdino de Oliveira | H84: Leonardo Galdino de Oliveira | I84: 2026-07-30 | J84: 2026-07-31 | K84: 2026-07-27 | M84: false | N84: 2026-07-31 | O84: Fernanda Sousa Araujo | T84: 645.92
A85: LuppmLo5wEWxlAY53tYdKmQAFXe9 | B85: Fazer a solicitação do Usuario da IA HeyGEn - Para produção de Videos do Programa de Melhorias | C85: =_xlfn.XLOOKUP(A85,Tarefas!A:A,Tarefas!C:C) -> Programa de Melhorias | E85: Concluída | F85: Importante | H85: Leonardo Costa da Silva | I85: 2026-07-30 | J85: 2026-07-31 | K85: 2026-07-20 | M85: false | N85: 2026-07-30 | O85: Leonardo Costa da Silva | T85: 301.13
A86: RnOEoxFvm0W2IL5gFQ49eGQAOe25 | B86: Revisar análise - Unir Tira, enformar prensar e desenformar - sorveteira a vácuo | C86: =_xlfn.XLOOKUP(A86,Tarefas!A:A,Tarefas!C:C) -> MTM/Impressão 3D | E86: Concluída | F86: Média | G86: Leonardo Galdino de Oliveira | H86: Leonardo Galdino de Oliveira | I86: 2026-07-30 | J86: 2026-07-31 | K86: 2026-07-27 | M86: false | N86: 2026-07-31 | O86: Fernanda Sousa Araujo | T86: 43.83
A87: L3GVZ9BgwUS52DIPmFLnNGQAF0JA | B87: Revisar análise - Aplicar Cola em sola, Área de Colagem da palmilha, Sola Cape Gaspea Adulto | C87: =_xlfn.XLOOKUP(A87,Tarefas!A:A,Tarefas!C:C) -> MTM/Impressão 3D | E87: Concluída | F87: Média | G87: Leonardo Galdino de Oliveira | H87: Leonardo Galdino de Oliveira | I87: 2026-07-30 | J87: 2026-07-31 | K87: 2026-07-27 | M87: false | N87: 2026-07-31 | O87: Fernanda Sousa Araujo | T87: 26.47
A88: nx6ETudwhkSZKF-DlV9LdmQAMmMc | B88: Liberar análise - Unir palmilha em cabedal com sola plataforma EVA + Enformar, Prensar e Desenformar, Sorveteira, Obter forma sem dedeira e Obter cabedal da esteira, Cabedal Com Tira de Fech | C88: =_xlfn.XLOOKUP(A88,Tarefas!A:A,Tarefas!C:C) -> MTM/Impressão 3D | E88: Concluída | F88: Média | G88: Leonardo Galdino de Oliveira | H88: Leonardo Galdino de Oliveira | I88: 2026-07-30 | J88: 2026-07-31 | K88: 2026-07-27 | M88: false | N88: 2026-07-31 | O88: Fernanda Sousa Araujo | T88: 776.96
A89: 1ddPje12i0ShFE3QmIWCtGQADlMD | B89: Criar análise - Passar sola pelo termoget, sola baixa, obter e dispor na esteira + Retirar fio de cola palmilha | C89: =_xlfn.XLOOKUP(A89,Tarefas!A:A,Tarefas!C:C) -> MTM/Impressão 3D | E89: Concluída | F89: Média | G89: Leonardo Galdino de Oliveira | H89: Leonardo Galdino de Oliveira | I89: 2026-07-30 | J89: 2026-07-31 | K89: 2026-07-27 | M89: false | N89: 2026-07-31 | O89: Fernanda Sousa Araujo | T89: 305.23
A90: IQagZw7PYEuAexzyqYIbdmQAHy6h | B90: Imprimir e Enviar formas do modelo 38154 para Fortaleza | C90: =_xlfn.XLOOKUP(A90,Tarefas!A:A,Tarefas!C:C) -> MTM/Impressão 3D | E90: Concluída | F90: Média | G90: Leonardo Galdino de Oliveira | H90: Leonardo Galdino de Oliveira | I90: 2026-07-30 | J90: 2026-07-31 | K90: 2026-07-27 | M90: false | N90: 2026-07-31 | O90: Fernanda Sousa Araujo | T90: 456.21
A91: 8KsST1BOoEK6Pf8uBKz-_WQAH0WU | B91: Ações de Planejamento Programa de Melhorias Mai-Jun26 | C91: =_xlfn.XLOOKUP(A91,Tarefas!A:A,Tarefas!C:C) -> Programa de Melhorias | E91: Concluída | F91: Média | G91: Leonardo Costa da Silva | H91: Leonardo Costa da Silva | I91: 2026-07-30 | J91: 2026-08-10 | K91: 2026-08-01 | M91: false | N91: 2026-08-14 | O91: Leonardo Costa da Silva | P91: 6/6 | Q91: Impressão dos Certificados;Criação da Apresentação do Evento;Impressão dos Cartões dos Premiados;Vídeo de Comunicação - Programa de Melhorias;Requisição dos calçados Programa de Melhorias - 03/08/2026;Requisição dos calçados Indicadores Internos - 29/07/2026 | T91: 715.98
A92: RQwDVlQdsUCAhihPeHJq82QAO_BU | B92: Desenhar e imprimir bases para placas laboratório | C92: =_xlfn.XLOOKUP(A92,Tarefas!A:A,Tarefas!C:C) -> MTM/Impressão 3D | E92: Concluída | F92: Média | G92: Leonardo Galdino de Oliveira | H92: Leonardo Galdino de Oliveira | I92: 2026-07-30 | J92: 2026-07-31 | K92: 2026-07-27 | M92: false | N92: 2026-07-31 | O92: Fernanda Sousa Araujo | T92: 671.96
A93: e_DhwMFXfkyGs6sRang6fGQAKO7a | B93: Revisar análise - Unir dedeira e palmilha no cabedal EVA, obter sola com palmilha já preso da esteira, dispor na esteira | C93: =_xlfn.XLOOKUP(A93,Tarefas!A:A,Tarefas!C:C) -> MTM/Impressão 3D | E93: Concluída | F93: Média | G93: Leonardo Galdino de Oliveira | H93: Leonardo Galdino de Oliveira | I93: 2026-07-30 | J93: 2026-07-31 | K93: 2026-07-27 | M93: false | N93: 2026-07-31 | O93: Fernanda Sousa Araujo | T93: 516.5
A94: IO8hRZVgcES2pP2D1qDU-2QAOXzT | B94: Fechar indicadores de Julho e Criar indicadores de Agosto | C94: =_xlfn.XLOOKUP(A94,Tarefas!A:A,Tarefas!C:C) -> Pendências Fechamento de Indicadores | E94: Concluída | F94: Média | G94: Leonardo Galdino de Oliveira | H94: Leonardo Galdino de Oliveira | I94: 2026-07-31 | J94: 2026-08-07 | K94: 2026-08-03 | M94: false | N94: 2026-08-14 | O94: Fernanda Sousa Araujo | P94: 11/13 | Q94: Melhoria TC;Auditoria 5S;Banco de Horas;Aprov. Estrutura Melissa;Passada Horizontal;Auditoria Produto Certificado;Melhoria MP;Aprov. Estrutura;Aderência MTM Melissa;Ineficiência;Aderência MTM;Certificação De produtos;Inclusão de batida | T94: 34.49
A95: EXBWHiRVBEiEsWb3GQzPnmQAIJGM | B95: Revisar análise - Limpar fio de cola, área da palmilha, com pincel, bico e calcanhar, obter simultâneo da esteira e dispor simultâneo, AD/INF | C95: =_xlfn.XLOOKUP(A95,Tarefas!A:A,Tarefas!C:C) -> MTM/Impressão 3D | E95: Concluída | F95: Média | G95: Leonardo Galdino de Oliveira | H95: Leonardo Galdino de Oliveira | I95: 2026-07-31 | J95: 2026-07-31 | K95: 2026-07-27 | M95: false | N95: 2026-07-31 | O95: Fernanda Sousa Araujo | T95: 504.98
A96: pcpJf9LytE6xf1yc5CQFg2QAFgYS | B96: Criar análise - Embutir cabedal na palmilha, 1 Dedeira + Aplicar Cola na Dedeira 3 áreas, com Bico de Pato Simples, Obter da esteira, Par | C96: =_xlfn.XLOOKUP(A96,Tarefas!A:A,Tarefas!C:C) -> MTM/Impressão 3D | E96: Concluída | F96: Média | G96: Leonardo Galdino de Oliveira | H96: Leonardo Galdino de Oliveira | I96: 2026-07-31 | J96: 2026-07-31 | K96: 2026-07-27 | M96: false | N96: 2026-07-31 | O96: Fernanda Sousa Araujo | T96: 990.77
A97: sbymhEvYZESsUZHJp03GD2QAFOku | B97: Acompanhamento de PPPs na hora das trocas de cor para verificar se realmente há problemas com o robô | C97: =_xlfn.XLOOKUP(A97,Tarefas!A:A,Tarefas!C:C) -> SMED | E97: Concluída | F97: Média | I97: 2026-07-31 | J97: 2026-07-31 | K97: 2026-07-27 | M97: false | N97: 2026-07-31 | T97: 9.8
A98: rNBhsyV_rUu6f7HcsUjo_mQAL8R3 | B98: Reunião com PPPs sobre custo do setup e premiação SMED | C98: =_xlfn.XLOOKUP(A98,Tarefas!A:A,Tarefas!C:C) -> SMED | E98: Em andamento | F98: Média | I98: 2026-07-31 | J98: 2026-08-13 | K98: 2026-07-20 | M98: true | P98: 5/6 | Q98: Fábrica 6 - 2° turno;Fábrica 1 - 2° turno;Fábrica 7 - 2° turno;Fábrica 6 - 1° turno;Fábrica 1 - 1° turno;Fábrica 7 - 1° turno | T98: 833.24
A99: ZjAN4YBVIESVi-rcfclTBWQADyss | B99: MOI - Sala de Tintas | C99: =_xlfn.XLOOKUP(A99,Tarefas!A:A,Tarefas!C:C) -> MOI, MOA, MODS | E99: Não iniciado | F99: Importante | G99: Charliane Batista de Alencar | H99: Charliane Batista de Alencar | I99: 2026-07-31 | J99: 2026-08-28 | K99: 2026-08-03 | M99: false | P99: 0/7 | Q99: Mapear todas as atividades realizadas na área e funções;Apresentar e validar com a gestão;Nova proposta de dimensionamento;Levantamento da situação atual;Testar nova proposta de dimensionamento;Lançar FAP;Verificar possíveis melhorias ou automações de processos | R99: Crato | T99: 784.14
A100: RY5Q6Ny2L0Wf47VKIVIN_GQAEBW- | B100: Acompanhar a aplicação dos Manifolds - Troca Rápida de Ar | C100: =_xlfn.XLOOKUP(A100,Tarefas!A:A,Tarefas!C:C) -> SMED | E100: Não iniciado | F100: Média | G100: Alan Feitosa Vilela | H100: Alan Feitosa Vilela | I100: 2026-07-31 | J100: 2026-08-07 | K100: 2026-08-03 | M100: true | P100: 0/3 | Q100: Gravar trocas utilizando o Manifold;Apresentar os resultados - Análise ECRS;Acompanhar a entrega de 26 Manifold's para os Trocadores | R100: Fortaleza | T100: 764.24
...

Sheet Tarefas
A1: Identificação da tarefa | B1: Nome da tarefa | D1: Categoria | E1: Meta | F1: Status | G1: Prioridade | H1: Atribuído a | I1: Criado por | J1: Criado em | K1: Data de conclusão | L1: Data de início | M1: É Recorrente | N1: Atrasados | O1: Concluído em | P1: Concluída por | Q1: Itens concluídos da lista de verificação | R1: Itens da lista de verificação | S1: Rótulos | T1: Notas
A2: mHYaQDYxrUiQ7uHDBJV_CGQAA0Bm | B2: Lançar melhoria do bimestre | C2: Programa de Melhorias | D2: KIfHiHgMjUeezxBeVZXLlmQABdnJ | F2: Não iniciado | G2: Média | H2: 63dd591c-960d-4c36-ad48-5b9197dc40ea;p_lylMOxR0ykz-6CgdD7JGQABhqd;3a4654ae-d002-45f0-a510-5a3d7e37c058;13401436-5972-4968-9178-08d3bcd592a4;8c3f18d2-9083-4819-8529-3d7d7f9bfbda | I2: 63dd591c-960d-4c36-ad48-5b9197dc40ea | J2: 2026-08-06 | K2: 2026-10-05 | N2: false | Q2: 0/10 | R2: Rômulo ;Charliane;Thiago Roberto;Martins;Leonardo Galdino;Kennedy;Leonardo Costa;Eduarda;Daniel Viana;Alan Vilela
A3: epEHIZFoYEawEMf2UmdnO2QAEl9u | B3: Lançar melhoria do bimestre | C3: Programa de Melhorias | D3: KIfHiHgMjUeezxBeVZXLlmQABdnJ | F3: Concluída | G3: Média | H3: 63dd591c-960d-4c36-ad48-5b9197dc40ea;p_lylMOxR0ykz-6CgdD7JGQABhqd;3a4654ae-d002-45f0-a510-5a3d7e37c058;13401436-5972-4968-9178-08d3bcd592a4;8c3f18d2-9083-4819-8529-3d7d7f9bfbda | I3: c40cc4cc-bdb3-454f-a193-cf3e59051c09 | J3: 2026-07-17 | K3: 2026-08-05 | N3: false | O3: 2026-08-06 | P3: 63dd591c-960d-4c36-ad48-5b9197dc40ea | Q3: 7/10 | R3: Rômulo ;Charliane;Thiago Roberto;Martins;Leonardo Galdino;Kennedy;Leonardo Costa;Eduarda;Daniel Viana;Alan Vilela
A4: 7SBLlTg6NUODyqgmnqwBnmQAPYN6 | B4: Lançar melhoria do bimestre | C4: Programa de Melhorias | D4: KIfHiHgMjUeezxBeVZXLlmQABdnJ | F4: Concluída | G4: Média | H4: 63dd591c-960d-4c36-ad48-5b9197dc40ea;b12ce1b5-2aa7-4f1d-b43a-272d90aabbe2;p_lylMOxR0ykz-6CgdD7JGQABhqd;3a4654ae-d002-45f0-a510-5a3d7e37c058;13401436-5972-4968-9178-08d3bcd592a4;8c3f18d2-9083-4819-8529-3d7d7f9bfbda | I4: c40cc4cc-bdb3-454f-a193-cf3e59051c09 | J4: 2026-07-17 | K4: 2026-04-05 | N4: false | O4: 2026-07-17 | P4: c40cc4cc-bdb3-454f-a193-cf3e59051c09 | Q4: 0/6 | R4: Rômulo ;Charliane;Martins;Kennedy;Douglas;Jennifer
A5: DRYwgOUmRUOgKzjzalMjq2QAAtiM | B5: Lançar melhoria do bimestre | C5: Programa de Melhorias | D5: KIfHiHgMjUeezxBeVZXLlmQABdnJ | F5: Concluída | G5: Média | H5: 63dd591c-960d-4c36-ad48-5b9197dc40ea;b12ce1b5-2aa7-4f1d-b43a-272d90aabbe2;p_lylMOxR0ykz-6CgdD7JGQABhqd;3a4654ae-d002-45f0-a510-5a3d7e37c058;13401436-5972-4968-9178-08d3bcd592a4;8c3f18d2-9083-4819-8529-3d7d7f9bfbda | I5: c40cc4cc-bdb3-454f-a193-cf3e59051c09 | J5: 2026-07-17 | K5: 2026-02-05 | N5: false | O5: 2026-07-17 | P5: c40cc4cc-bdb3-454f-a193-cf3e59051c09 | Q5: 0/6 | R5: Rômulo ;Charliane;Martins;Kennedy;Douglas;Jennifer
A6: F1LFUkS0RUu3Ibi25ZzRWWQAJj2X | B6: Lançar melhoria do bimestre | C6: Programa de Melhorias | D6: KIfHiHgMjUeezxBeVZXLlmQABdnJ | F6: Concluída | G6: Média | H6: 63dd591c-960d-4c36-ad48-5b9197dc40ea;b12ce1b5-2aa7-4f1d-b43a-272d90aabbe2;p_lylMOxR0ykz-6CgdD7JGQABhqd;3a4654ae-d002-45f0-a510-5a3d7e37c058;13401436-5972-4968-9178-08d3bcd592a4;8c3f18d2-9083-4819-8529-3d7d7f9bfbda | I6: c40cc4cc-bdb3-454f-a193-cf3e59051c09 | J6: 2026-07-17 | K6: 2025-12-05 | N6: false | O6: 2026-07-17 | P6: c40cc4cc-bdb3-454f-a193-cf3e59051c09 | Q6: 0/6 | R6: Rômulo ;Charliane;Martins;Kennedy;Douglas;Jennifer
A7: uQH-ZMJsr0CX1CPaui9Al2QAA1wN | B7: Lançar melhoria do bimestre | C7: Programa de Melhorias | D7: KIfHiHgMjUeezxBeVZXLlmQABdnJ | F7: Concluída | G7: Média | H7: 63dd591c-960d-4c36-ad48-5b9197dc40ea;b12ce1b5-2aa7-4f1d-b43a-272d90aabbe2;p_lylMOxR0ykz-6CgdD7JGQABhqd;3a4654ae-d002-45f0-a510-5a3d7e37c058;13401436-5972-4968-9178-08d3bcd592a4;8c3f18d2-9083-4819-8529-3d7d7f9bfbda | I7: c40cc4cc-bdb3-454f-a193-cf3e59051c09 | J7: 2026-07-17 | K7: 2025-10-05 | N7: false | O7: 2026-07-17 | P7: c40cc4cc-bdb3-454f-a193-cf3e59051c09 | Q7: 0/6 | R7: Rômulo ;Charliane;Martins;Kennedy;Douglas;Jennifer
A8: txeRybaODEq_PH978neS1mQAGaS0 | B8: Lançar melhoria do bimestre | C8: Programa de Melhorias | D8: KIfHiHgMjUeezxBeVZXLlmQABdnJ | F8: Concluída | G8: Média | H8: 63dd591c-960d-4c36-ad48-5b9197dc40ea;b12ce1b5-2aa7-4f1d-b43a-272d90aabbe2;p_lylMOxR0ykz-6CgdD7JGQABhqd;3a4654ae-d002-45f0-a510-5a3d7e37c058;13401436-5972-4968-9178-08d3bcd592a4;8c3f18d2-9083-4819-8529-3d7d7f9bfbda | I8: c40cc4cc-bdb3-454f-a193-cf3e59051c09 | J8: 2026-07-17 | K8: 2025-08-08 | N8: false | O8: 2026-07-17 | P8: c40cc4cc-bdb3-454f-a193-cf3e59051c09 | Q8: 0/6 | R8: Rômulo ;Charliane;Martins;Kennedy;Douglas;Jennifer
A9: tygljY6P00iU4kfls2vKV2QAG4Zo | B9: Lançar melhoria do bimestre | C9: Programa de Melhorias | D9: KIfHiHgMjUeezxBeVZXLlmQABdnJ | F9: Concluída | G9: Média | H9: 63dd591c-960d-4c36-ad48-5b9197dc40ea;b12ce1b5-2aa7-4f1d-b43a-272d90aabbe2;p_lylMOxR0ykz-6CgdD7JGQABhqd;3a4654ae-d002-45f0-a510-5a3d7e37c058;13401436-5972-4968-9178-08d3bcd592a4;8c3f18d2-9083-4819-8529-3d7d7f9bfbda | I9: c40cc4cc-bdb3-454f-a193-cf3e59051c09 | J9: 2026-07-17 | K9: 2024-12-05 | N9: false | O9: 2026-07-17 | P9: c40cc4cc-bdb3-454f-a193-cf3e59051c09 | Q9: 0/6 | R9: Rômulo ;Charliane;Martins;Kennedy;Douglas;Jennifer
A10: 22BLBarPRUGDpRVdEMXK-WQAIPMG | B10: Lançar melhoria do bimestre | C10: Programa de Melhorias | D10: KIfHiHgMjUeezxBeVZXLlmQABdnJ | F10: Concluída | G10: Média | H10: 63dd591c-960d-4c36-ad48-5b9197dc40ea;b12ce1b5-2aa7-4f1d-b43a-272d90aabbe2;p_lylMOxR0ykz-6CgdD7JGQABhqd;3a4654ae-d002-45f0-a510-5a3d7e37c058;13401436-5972-4968-9178-08d3bcd592a4;8c3f18d2-9083-4819-8529-3d7d7f9bfbda | I10: c40cc4cc-bdb3-454f-a193-cf3e59051c09 | J10: 2024-07-05 | K10: 2024-10-31 | N10: false | O10: 2026-07-17 | P10: c40cc4cc-bdb3-454f-a193-cf3e59051c09 | Q10: 0/6 | R10: Rômulo ;Charliane;Martins;Kennedy;Douglas;Jennifer
A11: XyQwFCHhokWxK8Qtp4qmkmQADVuN | B11: Fazer auditoria nos postos de trabalho dos lançamentos | C11: Tarefas Antigas | D11: KIfHiHgMjUeezxBeVZXLlmQABdnJ | F11: Concluída | G11: Média | H11: b12ce1b5-2aa7-4f1d-b43a-272d90aabbe2 | I11: c40cc4cc-bdb3-454f-a193-cf3e59051c09 | J11: 2024-07-25 | K11: 2024-08-30 | N11: false | O11: 2024-09-05 | P11: b12ce1b5-2aa7-4f1d-b43a-272d90aabbe2 | Q11: 4/4 | R11: Gerar laudo dos postos de trabalho e enviar para os envolvidos ;Registrar condições dos postos com fotos ;Analisar postos nos pilares de P5.0 e Ergonomia ;Passar nas linhas produtivas dos lançamentos | S11: Rotina
A12: Hl4x_KZhpkyOUlv5RxATVGQAM31J | B12: Criar as documentações do TEGAD dentro matrix | C12: Tarefas Antigas | D12: KIfHiHgMjUeezxBeVZXLlmQABdnJ | F12: Concluída | G12: Média | H12: vrAXgpRmkkiXVCuPMVArUmQAPEty | I12: c40cc4cc-bdb3-454f-a193-cf3e59051c09 | J12: 2024-07-25 | K12: 2024-08-02 | N12: false | O12: 2024-08-10 | P12: vrAXgpRmkkiXVCuPMVArUmQAPEty
A13: UjbIJMabvEC4WDGe9hiHvWQAK3Mj | B13: Criar as documentações dos montadores de layout dentro do matrix | C13: Tarefas Antigas | D13: KIfHiHgMjUeezxBeVZXLlmQABdnJ | F13: Concluída | G13: Média | H13: vrAXgpRmkkiXVCuPMVArUmQAPEty | I13: c40cc4cc-bdb3-454f-a193-cf3e59051c09 | J13: 2024-07-25 | K13: 2024-09-13 | N13: false | O13: 2026-07-17 | P13: c40cc4cc-bdb3-454f-a193-cf3e59051c09
A14: OxRSVcPgZEuV9LODx_vat2QAPkqZ | B14: Work sampling no processo de chamada ativa do PS7 | C14: Tarefas Antigas | D14: KIfHiHgMjUeezxBeVZXLlmQABdnJ | F14: Concluída | G14: Média | H14: 10FemLyfzUaLyDeuyzZepmQACfMU;p_lylMOxR0ykz-6CgdD7JGQABhqd | I14: c40cc4cc-bdb3-454f-a193-cf3e59051c09 | J14: 2024-07-25 | K14: 2024-08-23 | N14: false | O14: 2024-08-20 | P14: 10FemLyfzUaLyDeuyzZepmQACfMU | Q14: 4/4 | R14: Gerar um gráfico com os dados de percurso com maior repetição ;Registrar os percursos realizados de movimentação dos operadores ;Acompanhar o processo ;Anotar as ocorrências ou divergências do processo
A15: kTIeuZuHKk6LutwStQOPmWQAKOcl | B15: Cadastro de pessoas treinadas aplicativo. | C15: Tarefas Antigas | D15: KIfHiHgMjUeezxBeVZXLlmQABdnJ | F15: Concluída | G15: Média | H15: 10FemLyfzUaLyDeuyzZepmQACfMU;vrAXgpRmkkiXVCuPMVArUmQAPEty | I15: 10FemLyfzUaLyDeuyzZepmQACfMU | J15: 2024-07-25 | K15: 2024-08-23 | N15: false | O15: 2024-08-20 | P15: 10FemLyfzUaLyDeuyzZepmQACfMU | T15: Cadastrar listas de pessoas treinadas no aplicativo.
A16: HgnLevcgA0qC8e0NaziGdmQAAQrK | B16: Atualização planilhas SMED e criação de boletim. | C16: Tarefas Antigas | D16: KIfHiHgMjUeezxBeVZXLlmQABdnJ | F16: Concluída | G16: Média | H16: 10FemLyfzUaLyDeuyzZepmQACfMU;3a4654ae-d002-45f0-a510-5a3d7e37c058 | I16: 10FemLyfzUaLyDeuyzZepmQACfMU | J16: 2024-08-12 | K16: 2024-08-23 | N16: false | O16: 2024-08-20 | P16: 10FemLyfzUaLyDeuyzZepmQACfMU
A17: xZIuz0fqHEKGRIVvx_CjpGQAApIE | B17: Desenho | C17: Tarefas Antigas | D17: KIfHiHgMjUeezxBeVZXLlmQABdnJ | F17: Concluída | G17: Média | H17: vrAXgpRmkkiXVCuPMVArUmQAPEty | I17: vrAXgpRmkkiXVCuPMVArUmQAPEty | J17: 2024-08-13 | K17: 2024-08-16 | N17: false | O17: 2024-08-13 | P17: vrAXgpRmkkiXVCuPMVArUmQAPEty | Q17: 3/3 | R17: Desenho da Mesa Posto de trabalho F3;Desenho do Layout F3-F4;Desenho do Layout Peças Técnicas
A18: lDsMV28xPka_W5yxSGhSB2QAJ3v7 | B18: Atualização planilha dos indicadores | C18: Tarefas Antigas | D18: KIfHiHgMjUeezxBeVZXLlmQABdnJ | F18: Concluída | G18: Média | H18: 10FemLyfzUaLyDeuyzZepmQACfMU;vrAXgpRmkkiXVCuPMVArUmQAPEty | I18: vrAXgpRmkkiXVCuPMVArUmQAPEty | J18: 2024-08-20 | K18: 2024-08-21 | N18: false | O18: 2024-08-22 | P18: vrAXgpRmkkiXVCuPMVArUmQAPEty
A19: 8ZiKOBm8V0W1aszegn2HImQAO_b_ | B19: Atualizar checklist kaizen, ver com RH cadastro de pessoas treinadas em Kaizen. | C19: Tarefas Antigas | D19: KIfHiHgMjUeezxBeVZXLlmQABdnJ | F19: Concluída | G19: Média | H19: 10FemLyfzUaLyDeuyzZepmQACfMU;vrAXgpRmkkiXVCuPMVArUmQAPEty | I19: 10FemLyfzUaLyDeuyzZepmQACfMU | J19: 2024-08-20 | K19: 2024-08-21 | N19: false | O19: 2024-08-21 | P19: 10FemLyfzUaLyDeuyzZepmQACfMU
A20: H1uUhGXRGU-77B3fs6q8LmQANBpP | B20: Organização materiais MEG | C20: Tarefas Antigas | D20: KIfHiHgMjUeezxBeVZXLlmQABdnJ | F20: Concluída | G20: Média | H20: 10FemLyfzUaLyDeuyzZepmQACfMU;vrAXgpRmkkiXVCuPMVArUmQAPEty | I20: 10FemLyfzUaLyDeuyzZepmQACfMU | J20: 2024-08-20 | K20: 2024-09-12 | N20: false | O20: 2026-07-17 | P20: c40cc4cc-bdb3-454f-a193-cf3e59051c09
A21: 1jM1QpSMA02fNwk_HDPi_mQAKDS8 | B21: Estudo Sala Impressão Digital | C21: Tarefas Antigas | D21: KIfHiHgMjUeezxBeVZXLlmQABdnJ | F21: Concluída | G21: Média | H21: 10FemLyfzUaLyDeuyzZepmQACfMU | I21: 10FemLyfzUaLyDeuyzZepmQACfMU | J21: 2024-08-20 | K21: 2024-09-18 | N21: false | O21: 2026-07-17 | P21: c40cc4cc-bdb3-454f-a193-cf3e59051c09
A22: cQO-fezfA0eUz3P6IidJkGQABDk8 | B22: Organizar evento de melhorias | C22: Tarefas Antigas | D22: KIfHiHgMjUeezxBeVZXLlmQABdnJ | F22: Concluída | G22: Média | H22: b12ce1b5-2aa7-4f1d-b43a-272d90aabbe2 | I22: c40cc4cc-bdb3-454f-a193-cf3e59051c09 | J22: 2024-09-27 | K22: 2024-09-24 | N22: false | O22: 2024-09-27 | P22: c40cc4cc-bdb3-454f-a193-cf3e59051c09 | Q22: 5/5 | R22: Organizar o espaço de eventos ;Montar apresentação do evento ;Listar os dados dos premiados (Calçados e informações gerais);Levantar dados das avaliações de percepção. ;Treinar a apresentação
A23: SZ2NF2FBAE-UeRtXURXbLmQANNYa | B23: Passada Horizontal no TS6 | C23: Tarefas Antigas | D23: KIfHiHgMjUeezxBeVZXLlmQABdnJ | F23: Concluída | G23: Média | H23: b12ce1b5-2aa7-4f1d-b43a-272d90aabbe2 | I23: c40cc4cc-bdb3-454f-a193-cf3e59051c09 | J23: 2024-09-27 | K23: 2024-09-27 | N23: false | O23: 2024-09-27 | P23: c40cc4cc-bdb3-454f-a193-cf3e59051c09
A24: DjnKbRcTlEar2AF5aYS1g2QAJm8W | B24: Passada Horizontal TS7 | C24: Tarefas Antigas | D24: KIfHiHgMjUeezxBeVZXLlmQABdnJ | F24: Concluída | G24: Média | H24: b12ce1b5-2aa7-4f1d-b43a-272d90aabbe2 | I24: c40cc4cc-bdb3-454f-a193-cf3e59051c09 | J24: 2024-09-27 | K24: 2024-09-25 | N24: false | O24: 2024-09-27 | P24: c40cc4cc-bdb3-454f-a193-cf3e59051c09
A25: LQZZqn7VwUm8GsQfpC4GhGQADMSP | B25: MOI - Movimentadores de Caixas Montagem | C25: =_xlfn.XLOOKUP(D25,Buckets!A:A,Buckets!B:B) -> MOI, MOA, MODS | D25: QKOg4Hdgj0ivgeBuZ62ybmQAI-jH | E25: UIsKR4azC0aIhKUlTIZKCWQAAOHD | F25: Em andamento | G25: Importante | H25: 8c3f18d2-9083-4819-8529-3d7d7f9bfbda | I25: 8c3f18d2-9083-4819-8529-3d7d7f9bfbda | J25: 2026-07-17 | K25: 2026-07-24 | L25: 2026-07-06 | N25: true | Q25: 6/8 | R25: Validar com a gestão;Determinar padrões da operações;Testar nova proposta;Verificar possíveis propostas de melhorias ou automações;Avaliar durante uma semana dimensionamento pro fator X Padrão / aglutinado;Lançar FAP;Criar nova proposta de dimensionamento;Levantar situação atual | S25: Crato
A26: NkewH3A-5Eail--FODKxU2QAH1YF | B26: Otimização Setup Matriz EVA | C26: =_xlfn.XLOOKUP(D26,Buckets!A:A,Buckets!B:B) -> SMED | D26: 1XwoBpXjJ02mmuVIAeaTAGQAGr4T | E26: CPyA7_JXT0Ot246svFbgKWQADc9O | F26: Não iniciado | G26: Média | H26: 63dd591c-960d-4c36-ad48-5b9197dc40ea;07a2aff1-4a07-48ba-8ada-daf14a19fd85 | I26: 63dd591c-960d-4c36-ad48-5b9197dc40ea | J26: 2026-07-17 | K26: 2026-08-31 | L26: 2026-07-20 | N26: false | Q26: 5/9 | R26: Acompanhar definição do carrinho compra ou confecção junto a fábrica;Análise de ganho para transformação das matrizes em troca rápida (Vagner).;Análise de setups Matriz. (20 à 24/07);Acompanhamento de implantação do Simon.;Teste de carrinho com capacidade para matrizes de entrada e saída.;Fazer analise do custo da estufa ligada o dia todo (Setups por maquina e por dia);Teste de pré aquecimento de matriz em setups reais.;Análise do fluxo de programação do EVA.;Montar material para reunião com Igor (sobre a estufa e moer purga)
A27: sNUu7Jc6NkyzqxvlG4HlcGQANkch | B27: Cerimônia de Premiação do Programa de Melhorias | C27: =_xlfn.XLOOKUP(D27,Buckets!A:A,Buckets!B:B) -> Programa de Melhorias | D27: NHhoi0Q460Owj98eJ_OOMmQANgsZ | F27: Em andamento | G27: Média | H27: 05f35150-a826-4040-9362-c540d816ffd0 | I27: 05f35150-a826-4040-9362-c540d816ffd0 | J27: 2026-07-17 | K27: 2026-12-31 | N27: false | Q27: 1/4 | R27: Cerimônia de Premiação - Bimestre Set/Out 2026;Cerimônia de Premiação - Bimestre Jul/Ago 2026;Cerimônia de Premiação - Bimestre Mai/Jun 2026;Cerimônia de Premiação - Bimestre Nov/Dez 2026
A28: Rs5Oc-Bkx02tuG9Y-sk0lGQAMxXl | B28: MOI - Auxiliar de Matrizaria | C28: =_xlfn.XLOOKUP(D28,Buckets!A:A,Buckets!B:B) -> MOI, MOA, MODS | D28: QKOg4Hdgj0ivgeBuZ62ybmQAI-jH | E28: UIsKR4azC0aIhKUlTIZKCWQAAOHD | F28: Em andamento | G28: Importante | H28: 8c3f18d2-9083-4819-8529-3d7d7f9bfbda | I28: 8c3f18d2-9083-4819-8529-3d7d7f9bfbda | J28: 2026-07-17 | K28: 2026-07-22 | L28: 2026-07-06 | N28: true | Q28: 9/10 | R28: Validar com a gestão;Tabulação de dados e classificação das atividades;Acompanhar turno B;Apresentar a gerência e coordenação;Verificar possíveis propostas de melhorias, transferências ou otimização de atividades;Colocar em teste para avaliar;Proposta de novo dimensionamento;Verificar com Kleilson a decisão de alterar dimensionamento, conforme avaliação no físico;Lançar FAP;Acompanhamento turno A (07/07 e 09/07) | S28: Crato
A29: t8_qJepIiUqnTdiC4yZkT2QAI7ze | B29: MOI - Matrizeiro | C29: =_xlfn.XLOOKUP(D29,Buckets!A:A,Buckets!B:B) -> MOI, MOA, MODS | D29: QKOg4Hdgj0ivgeBuZ62ybmQAI-jH | E29: UIsKR4azC0aIhKUlTIZKCWQAAOHD | F29: Não iniciado | G29: Importante | I29: 8c3f18d2-9083-4819-8529-3d7d7f9bfbda | J29: 2026-07-17 | N29: false | Q29: 0/8 | R29: Tabulação de dados e classificação das atividades;Proposta de novo dimensionamento;Colocar em teste para avaliar;Validar com a gestão;Acompanhamento turno A;Acompanhar turno B;Lançar FAP;Verificar possíveis propostas de melhorias, transferências ou otimização de atividades | S29: Crato
A30: XD1eWNDN_ECyHQuAr9pQImQAJevi | B30: SMED Setup de Cor EVA | C30: =_xlfn.XLOOKUP(D30,Buckets!A:A,Buckets!B:B) -> SMED | D30: 1XwoBpXjJ02mmuVIAeaTAGQAGr4T | E30: CPyA7_JXT0Ot246svFbgKWQADc9O | F30: Não iniciado | G30: Média | H30: 63dd591c-960d-4c36-ad48-5b9197dc40ea;07a2aff1-4a07-48ba-8ada-daf14a19fd85 | I30: 63dd591c-960d-4c36-ad48-5b9197dc40ea | J30: 2026-07-17 | K30: 2026-10-31 | N30: false | Q30: 5/7 | R30: Análise da troca de cor sem a utilização do material de limpeza.;Análise ECRS - Troca de cor simples e complexa;Análise de tempo perdido com expurgo, recorte e recolhimento da purga.;Proposta de alterações para redução de material expurgado (Reduzir material dentro do injetor).;Realizar teste no mini moinho com a purga do EVA para ver o comportamento do material.;Criar mapa de raciocínio da troca de cor;Levantamento de ganhos.
A31: DoKMHOwn7UCOR_vLrOHv3mQAHbad | B31: MOI - Tegad / Célula de Layout | C31: =_xlfn.XLOOKUP(D31,Buckets!A:A,Buckets!B:B) -> MOI, MOA, MODS | D31: QKOg4Hdgj0ivgeBuZ62ybmQAI-jH | E31: UIsKR4azC0aIhKUlTIZKCWQAAOHD | F31: Em andamento | G31: Importante | H31: 3a4654ae-d002-45f0-a510-5a3d7e37c058;8c3f18d2-9083-4819-8529-3d7d7f9bfbda | I31: 8c3f18d2-9083-4819-8529-3d7d7f9bfbda | J31: 2026-07-17 | L31: 2026-07-13 | N31: false | Q31: 4/7 | R31: Levantamento da situação atual;Apresentar e validar com a gestão;Mapear todas as atividades realizadas na área e funções;Lançar FAP;Testar nova proposta de dimensionamento;Verificar possíveis melhorias ou automações de processos;Nova proposta de dimensionamento | T31: Link Apresentação: https://canva.link/h3vnpu6cgzovy20
A32: HXKuxw-cBUepbRalBZSt1mQAKYct | B32: Credenciamento - Programa de Melhorias | C32: =_xlfn.XLOOKUP(D32,Buckets!A:A,Buckets!B:B) -> Programa de Melhorias | D32: NHhoi0Q460Owj98eJ_OOMmQANgsZ | E32: _TclC5XyU0itQqOSRgoOa2QAB9Fw | F32: Concluída | G32: Média | H32: 05f35150-a826-4040-9362-c540d816ffd0 | I32: 05f35150-a826-4040-9362-c540d816ffd0 | J32: 2026-07-17 | K32: 2026-07-22 | N32: false | O32: 2026-07-24 | P32: 05f35150-a826-4040-9362-c540d816ffd0 | Q32: 2/2 | R32: Reunião para montagem do Plano de Credenciamento do Programa de Melhorias;Estruturar o conteúdo de Treinamento para o Público de Preparadores ate Supervisão | T32: Foi criado o Manual com o objetivo de conduzir o conteudo para TReinamento para o Publico, abordando sobre o programa de Melhorias, o seu funcionamento, bem como, o planejamento da cerimônia de premiação.
A33: V0yIkFtIWEOskxThXpxkY2QAM3ON | B33: Padronização das Embalagens | C33: =_xlfn.XLOOKUP(D33,Buckets!A:A,Buckets!B:B) -> Padronizações/Certificações | D33: jcA3eTZpVESyCtCrwdC8t2QAAqf5 | F33: Não iniciado | G33: Média | H33: 05f35150-a826-4040-9362-c540d816ffd0 | I33: 05f35150-a826-4040-9362-c540d816ffd0 | J33: 2026-07-17 | K33: 2026-08-31 | N33: false | Q33: 0/4 | R33: Mobiliários - Crato;Mobiliarios - Fortaleza;Criação do material de apresentação da Hora da Excelência - Padronização das Embalagens;Mobiliários - Sobral
A34: CX98n3yEK0mDhVfC_Fi1J2QAHMG- | B34: Padronização das Salas de Tintas | C34: =_xlfn.XLOOKUP(D34,Buckets!A:A,Buckets!B:B) -> Padronizações/Certificações | D34: jcA3eTZpVESyCtCrwdC8t2QAAqf5 | F34: Não iniciado | G34: Média | I34: 05f35150-a826-4040-9362-c540d816ffd0 | J34: 2026-07-17 | N34: false
A35: hiwXVtGDc0-i01bBHDNL72QANeXx | B35: Padronização do Tingimento | C35: =_xlfn.XLOOKUP(D35,Buckets!A:A,Buckets!B:B) -> Padronizações/Certificações | D35: jcA3eTZpVESyCtCrwdC8t2QAAqf5 | F35: Não iniciado | G35: Média | I35: 05f35150-a826-4040-9362-c540d816ffd0 | J35: 2026-07-17 | N35: false
A36: ZdZflJXSmkK-wVFOke3F5GQAP5-z | B36: [Semana 27-31/07] Automação de atividades de Organização do Programa de Melhorias | C36: =_xlfn.XLOOKUP(D36,Buckets!A:A,Buckets!B:B) -> Programa de Melhorias | D36: NHhoi0Q460Owj98eJ_OOMmQANgsZ | F36: Em andamento | G36: Média | H36: 9686d721-f970-4664-808d-2b7eccd6564a | I36: 05f35150-a826-4040-9362-c540d816ffd0 | J36: 2026-07-17 | K36: 2026-07-31 | N36: true | Q36: 1/5 | R36: Automatizar montagem da apresentação do Programa de Melhorias;Analise dos arquivos e dos fluxos para viabilizar automação;Automatizar montagem dos Certificados;Automatizar Convite dos Premiados e Convite Oficial para Gerencias do Programa de Melhorias;Criação dos arquivos do material de planejamento em pasta para automação
A37: Yvny0_yZ00u0pFkafmUt9mQAFqat | B37: Criar operação de aplicar rolinho curvado logo pequeno | C37: =_xlfn.XLOOKUP(D37,Buckets!A:A,Buckets!B:B) -> MTM/Impressão 3D | D37: 68oi7tmPFkWnLtIUxxbIyGQAGAus | F37: Concluída | G37: Média | H37: 1c74a3a3-f72d-417f-97b2-b50d886d5068 | I37: 1c74a3a3-f72d-417f-97b2-b50d886d5068 | J37: 2026-07-17 | K37: 2026-07-24 | L37: 2026-07-20 | N37: false | O37: 2026-07-30 | P37: 1c74a3a3-f72d-417f-97b2-b50d886d5068
A38: zuLDstg9b0efs3su_Ph4fGQAIxsY | B38: Montar apresentação para treinamento novo dosador | C38: =_xlfn.XLOOKUP(D38,Buckets!A:A,Buckets!B:B) -> Padronizações/Certificações | D38: jcA3eTZpVESyCtCrwdC8t2QAAqf5 | F38: Não iniciado | G38: Média | H38: 1c74a3a3-f72d-417f-97b2-b50d886d5068 | I38: 1c74a3a3-f72d-417f-97b2-b50d886d5068 | J38: 2026-07-17 | K38: 2026-07-24 | L38: 2026-07-20 | N38: true
A39: VielfIXtXEiR6oY1QY6E5GQABVwj | B39: [Semana 20-24/07] Criação dos Famílias - Serigrafia Fábrica 05 | C39: =_xlfn.XLOOKUP(D39,Buckets!A:A,Buckets!B:B) -> RPA | D39: rMSwZXAoc0e0KRod7mGv3mQAO_ax | F39: Concluída | G39: Urgente | H39: dfffd270-6981-4011-8fa1-759e71d9f99e | I39: dfffd270-6981-4011-8fa1-759e71d9f99e | J39: 2026-07-17 | K39: 2026-07-24 | L39: 2026-07-01 | N39: false | O39: 2026-07-23 | P39: dfffd270-6981-4011-8fa1-759e71d9f99e | Q39: 5/5 | R39: Levantar dados de processo de Serigrafia da Fábrica 05;Criar bases de famílias e gráficos para visualização da distribuição das Famílias;Analisar os padrões p/lacas/hr dos modelos para criar os ranges das Famílias;Levantar dados de PQP;Analisar os padrões pares/hr dos modelos para criar os ranges das Famílias
A40: qDcgfgf80kykqSwwa8PPaWQAFFo8 | B40: Projeto TR Cabine de Pintura Manual | C40: =_xlfn.XLOOKUP(D40,Buckets!A:A,Buckets!B:B) -> SMED | D40: 1XwoBpXjJ02mmuVIAeaTAGQAGr4T | E40: UIsKR4azC0aIhKUlTIZKCWQAAOHD | F40: Em andamento | G40: Importante | H40: 63dd591c-960d-4c36-ad48-5b9197dc40ea | I40: fd56df57-6763-4283-b5e9-97b57478fb7a | J40: 2026-07-18 | K40: 2026-08-31 | N40: false | Q40: 0/3 | R40: Confecção de bombas TS7 (nec. 32/ feito 18);Replicação para TS6 (nec. 26);Replicação para TS1 (nec. 12)
A41: PsqUFHQh2EmWCDzylxrMEWQAMyNp | B41: Enviar boletim de Aderência de Melhorias - Quinzenal para Gerentes e Coordenadores | C41: =_xlfn.XLOOKUP(D41,Buckets!A:A,Buckets!B:B) -> Programa de Melhorias | D41: NHhoi0Q460Owj98eJ_OOMmQANgsZ | F41: Não iniciado | G41: Média | H41: 05f35150-a826-4040-9362-c540d816ffd0 | I41: 05f35150-a826-4040-9362-c540d816ffd0 | J41: 2026-07-18 | K41: 2026-12-31 | L41: 2026-08-01 | N41: false | T41: Adicionar informações relacionadas ao Programa de Melhorias - Aderencia de Melhorias, Aderencia das Ideias do QRCode, Visão geral das gerencias e o impacto financeiro.
A42: hz469tm0u0-84IeJuXfluGQAIrdx | B42: Enviar boletim semanal relacionado a Gestão de Melhorias da área do Tiago - Engenharia | C42: =_xlfn.XLOOKUP(D42,Buckets!A:A,Buckets!B:B) -> Programa de Melhorias | D42: NHhoi0Q460Owj98eJ_OOMmQANgsZ | F42: Não iniciado | G42: Média | H42: 05f35150-a826-4040-9362-c540d816ffd0 | I42: c40cc4cc-bdb3-454f-a193-cf3e59051c09 | J42: 2026-08-14 | K42: 2026-08-18 | L42: 2026-08-13 | N42: false
A43: 08E3NE5cTEq1sd_TzjrEVWQALWnl | B43: Enviar boletim semanal relacionado a Gestão de Melhorias da área do Tiago - Engenharia | C43: =_xlfn.XLOOKUP(D43,Buckets!A:A,Buckets!B:B) -> Programa de Melhorias | D43: NHhoi0Q460Owj98eJ_OOMmQANgsZ | F43: Concluída | G43: Média | H43: 05f35150-a826-4040-9362-c540d816ffd0 | I43: c40cc4cc-bdb3-454f-a193-cf3e59051c09 | J43: 2026-08-14 | K43: 2026-08-11 | L43: 2026-08-06 | N43: false | O43: 2026-08-14 | P43: c40cc4cc-bdb3-454f-a193-cf3e59051c09
A44: vyEptvuaskOXeZr0cHELf2QAETqG | B44: Enviar boletim semanal relacionado a Gestão de Melhorias da área do Tiago - Engenharia | C44: =_xlfn.XLOOKUP(D44,Buckets!A:A,Buckets!B:B) -> Programa de Melhorias | D44: NHhoi0Q460Owj98eJ_OOMmQANgsZ | F44: Concluída | G44: Média | H44: 05f35150-a826-4040-9362-c540d816ffd0 | I44: 05f35150-a826-4040-9362-c540d816ffd0 | J44: 2026-07-23 | K44: 2026-08-06 | L44: 2026-08-01 | N44: false | O44: 2026-08-14 | P44: c40cc4cc-bdb3-454f-a193-cf3e59051c09
A45: ezE1p0UcT0yNxkv7BuF1a2QAKUsr | B45: Enviar boletim semanal relacionado a Gestão de Melhorias da área do Tiago - Engenharia | C45: =_xlfn.XLOOKUP(D45,Buckets!A:A,Buckets!B:B) -> Programa de Melhorias | D45: NHhoi0Q460Owj98eJ_OOMmQANgsZ | F45: Concluída | G45: Média | H45: 05f35150-a826-4040-9362-c540d816ffd0 | I45: 05f35150-a826-4040-9362-c540d816ffd0 | J45: 2026-07-18 | K45: 2026-07-21 | L45: 2026-07-17 | N45: false | O45: 2026-07-22 | P45: 05f35150-a826-4040-9362-c540d816ffd0
A46: tS3ynbJ2PUmw2ahAWkxC3WQAGf5h | B46: Criar operação de montar enfeite com novo equipamento | C46: =_xlfn.XLOOKUP(D46,Buckets!A:A,Buckets!B:B) -> MTM/Impressão 3D | D46: 68oi7tmPFkWnLtIUxxbIyGQAGAus | F46: Concluída | G46: Média | H46: 1c74a3a3-f72d-417f-97b2-b50d886d5068 | I46: 1c74a3a3-f72d-417f-97b2-b50d886d5068 | J46: 2026-07-18 | K46: 2026-07-24 | L46: 2026-07-20 | N46: false | O46: 2026-07-30 | P46: 1c74a3a3-f72d-417f-97b2-b50d886d5068
A47: CuZgcze8_UKVNKhnXWgm1WQAN6E8 | B47: Acompanhar entrega dos móveis embalagem | C47: =_xlfn.XLOOKUP(D47,Buckets!A:A,Buckets!B:B) -> Padronizações/Certificações | D47: jcA3eTZpVESyCtCrwdC8t2QAAqf5 | F47: Não iniciado | G47: Média | H47: 1c74a3a3-f72d-417f-97b2-b50d886d5068 | I47: 1c74a3a3-f72d-417f-97b2-b50d886d5068 | J47: 2026-07-18 | K47: 2026-12-31 | L47: 2026-07-20 | N47: false
A48: IcdR8JEto02P-PM5dTzhGmQALFKt | B48: Acompanhar entrega das bombas duplas | C48: =_xlfn.XLOOKUP(D48,Buckets!A:A,Buckets!B:B) -> Padronizações/Certificações | D48: jcA3eTZpVESyCtCrwdC8t2QAAqf5 | F48: Não iniciado | G48: Média | H48: 1c74a3a3-f72d-417f-97b2-b50d886d5068 | I48: 1c74a3a3-f72d-417f-97b2-b50d886d5068 | J48: 2026-07-18 | K48: 2026-08-28 | L48: 2026-07-20 | N48: false | Q48: 0/5 | R48: F1 - Total - 12, entregue - 7;F7 - Total - 38, entregue - 21;Previsão de entrega 28/08/2026;F6 - Total - 26, entregue - 6;33 bombas entregues Atualização - 14/08/2026
A49: 0vsw8n4Q7Ei7dKijGz-ZuGQAJRQY | B49: Projeto 02 - Dimensionamento dos Trocadores de Layout Fáb. 06 | C49: =_xlfn.XLOOKUP(D49,Buckets!A:A,Buckets!B:B) -> MOI, MOA, MODS | D49: QKOg4Hdgj0ivgeBuZ62ybmQAI-jH | E49: UIsKR4azC0aIhKUlTIZKCWQAAOHD | F49: Não iniciado | G49: Média | H49: 3a4654ae-d002-45f0-a510-5a3d7e37c058 | I49: 3a4654ae-d002-45f0-a510-5a3d7e37c058 | J49: 2026-07-18 | K49: 2026-08-14 | N49: true | Q49: 3/4 | R49: Acompanhar físico x tabela de cálculo.;Criar tabela de dimensionamento da F06;Validar processo de dimensionamento hora a hora.;Testar processo de automação das informações
A50: 3kqVaLHdgUuM5WHpeu2VF2QAPOok | B50: Fazer análise de ganhos dos modelos com elevador | C50: =_xlfn.XLOOKUP(D50,Buckets!A:A,Buckets!B:B) -> MTM/Impressão 3D | D50: 68oi7tmPFkWnLtIUxxbIyGQAGAus | F50: Concluída | G50: Média | H50: 1c74a3a3-f72d-417f-97b2-b50d886d5068 | I50: 1c74a3a3-f72d-417f-97b2-b50d886d5068 | J50: 2026-07-18 | K50: 2026-07-21 | L50: 2026-07-20 | N50: false | O50: 2026-07-23 | P50: 1c74a3a3-f72d-417f-97b2-b50d886d5068
A51: EdGjdxfvPke8i4ykf3f3Y2QAEcAO | B51: Atualização dos ganhos dos robôs de pintura | C51: =_xlfn.XLOOKUP(D51,Buckets!A:A,Buckets!B:B) -> Padronizações/Certificações | D51: jcA3eTZpVESyCtCrwdC8t2QAAqf5 | F51: Em andamento | G51: Importante | H51: 1c74a3a3-f72d-417f-97b2-b50d886d5068 | I51: 1c74a3a3-f72d-417f-97b2-b50d886d5068 | J51: 2026-07-20 | K51: 2026-12-31 | L51: 2026-07-20 | N51: false
A52: Yo4Dt-bPr06xy8GLKPU6mWQAC7So | B52: Projeto 02 - Dimensionamento dos Trocadores de Layout Fáb. 07 | C52: =_xlfn.XLOOKUP(D52,Buckets!A:A,Buckets!B:B) -> MOI, MOA, MODS | D52: QKOg4Hdgj0ivgeBuZ62ybmQAI-jH | E52: UIsKR4azC0aIhKUlTIZKCWQAAOHD | F52: Não iniciado | G52: Média | I52: c40cc4cc-bdb3-454f-a193-cf3e59051c09 | J52: 2026-07-20 | N52: false | Q52: 0/4 | R52: Testar processo de automação das informações;Criar tabela de dimensionamento;Acompanhar físico x tabela de cálculo.;Validar processo de dimensionamento hora a hora.
A53: -xACx8adIU6pxoiKRb2o52QAAkJJ | B53: Projeto 02 - Dimensionamento dos Trocadores de Layout Crato | C53: =_xlfn.XLOOKUP(D53,Buckets!A:A,Buckets!B:B) -> MOI, MOA, MODS | D53: QKOg4Hdgj0ivgeBuZ62ybmQAI-jH | E53: UIsKR4azC0aIhKUlTIZKCWQAAOHD | F53: Não iniciado | G53: Média | H53: 3a4654ae-d002-45f0-a510-5a3d7e37c058 | I53: c40cc4cc-bdb3-454f-a193-cf3e59051c09 | J53: 2026-07-20 | N53: false | Q53: 0/4 | R53: Testar processo de automação das informações;Criar tabela de dimensionamento;Acompanhar físico x tabela de cálculo.;Validar processo de dimensionamento hora a hora.
A54: S92B9tmFzkGOmEApomfXDmQAGULD | B54: Projeto 02 - Dimensionamento dos Trocadores de Layout Fáb. 01 | C54: =_xlfn.XLOOKUP(D54,Buckets!A:A,Buckets!B:B) -> MOI, MOA, MODS | D54: QKOg4Hdgj0ivgeBuZ62ybmQAI-jH | E54: UIsKR4azC0aIhKUlTIZKCWQAAOHD | F54: Não iniciado | G54: Média | H54: 3a4654ae-d002-45f0-a510-5a3d7e37c058 | I54: c40cc4cc-bdb3-454f-a193-cf3e59051c09 | J54: 2026-07-20 | N54: false | Q54: 0/4 | R54: Testar processo de automação das informações;Validar processo de dimensionamento hora a hora.;Criar tabela de dimensionamento;Acompanhar físico x tabela de cálculo.
A55: o96uDVPn7kO1BO1Et1ngDWQADbuj | B55: Projeto 01 - Dimensionamento dos Reguladores de Telas | C55: =_xlfn.XLOOKUP(D55,Buckets!A:A,Buckets!B:B) -> MOI, MOA, MODS | D55: QKOg4Hdgj0ivgeBuZ62ybmQAI-jH | E55: UIsKR4azC0aIhKUlTIZKCWQAAOHD | F55: Concluída | G55: Média | H55: 3a4654ae-d002-45f0-a510-5a3d7e37c058 | I55: c40cc4cc-bdb3-454f-a193-cf3e59051c09 | J55: 2026-07-20 | K55: 2026-07-31 | N55: false | O55: 2026-07-20 | P55: c40cc4cc-bdb3-454f-a193-cf3e59051c09 | Q55: 5/5 | R55: Criar tabela de cálculo do dimensionamento;Adequar e validar o quadro de acordo com a demanda.;Aplicar automação de processo da tabela de cálculo;Acompanhar físico x Tabela de cálculo;Lançar FAP
A56: ZoTDwBVfnEmPgFXlKmTqjWQACeHJ | B56: Levantamento das atividades de assistentes | C56: =_xlfn.XLOOKUP(D56,Buckets!A:A,Buckets!B:B) -> RPA | D56: rMSwZXAoc0e0KRod7mGv3mQAO_ax | F56: Concluída | G56: Média | H56: 9686d721-f970-4664-808d-2b7eccd6564a | I56: 9686d721-f970-4664-808d-2b7eccd6564a | J56: 2026-07-21 | K56: 2026-07-17 | N56: false | O56: 2026-08-14 | P56: 05f35150-a826-4040-9362-c540d816ffd0 | Q56: 5/5 | R56: Atividades Expandido/EVA;Atividades F3;Atividades TS;Levantamento das atividades automatizadas;Atividades F5
A57: BviPoBNEQkqKe9OduuH0yGQABFvA | B57: BI - Dados de Try out | C57: =_xlfn.XLOOKUP(D57,Buckets!A:A,Buckets!B:B) -> RPA | D57: rMSwZXAoc0e0KRod7mGv3mQAO_ax | F57: Concluída | G57: Média | H57: 9686d721-f970-4664-808d-2b7eccd6564a | I57: 9686d721-f970-4664-808d-2b7eccd6564a | J57: 2026-07-21 | K57: 2026-07-17 | N57: false | O57: 2026-07-23 | P57: 9686d721-f970-4664-808d-2b7eccd6564a
A58: LanAVr4K706TZ6Q0KnKk12QAOVHp | B58: Atualização Automação Robô de Pintura | C58: =_xlfn.XLOOKUP(D58,Buckets!A:A,Buckets!B:B) -> RPA | D58: rMSwZXAoc0e0KRod7mGv3mQAO_ax | F58: Não iniciado | G58: Baixa | H58: 9686d721-f970-4664-808d-2b7eccd6564a | I58: 9686d721-f970-4664-808d-2b7eccd6564a | J58: 2026-07-21 | K58: 2026-07-17 | N58: true | T58: Devido a prioridade da revisão do indicador de aproveitamento de estrutura não foi possível concluir a atividade.
A59: -WOhHxUVG0uivvr_8oCQf2QANUxA | B59: Indicadores Internos Engenharia | C59: =_xlfn.XLOOKUP(D59,Buckets!A:A,Buckets!B:B) -> RPA | D59: rMSwZXAoc0e0KRod7mGv3mQAO_ax | F59: Concluída | G59: Média | H59: 9686d721-f970-4664-808d-2b7eccd6564a;05f35150-a826-4040-9362-c540d816ffd0 | I59: 9686d721-f970-4664-808d-2b7eccd6564a | J59: 2026-07-21 | K59: 2026-07-30 | N59: false | O59: 2026-07-31 | P59: 9686d721-f970-4664-808d-2b7eccd6564a | Q59: 5/5 | R59: Certificado;Apresentação;Projetos de Engenharia;Requisitar calçados;Kahoot
A60: 2rd8eeiMKk-jy8_LpN3712QAFQiE | B60: Replicação - Automação de download de documentação Matrix | C60: =_xlfn.XLOOKUP(D60,Buckets!A:A,Buckets!B:B) -> RPA | D60: rMSwZXAoc0e0KRod7mGv3mQAO_ax | F60: Em andamento | G60: Média | H60: 9686d721-f970-4664-808d-2b7eccd6564a | I60: 9686d721-f970-4664-808d-2b7eccd6564a | J60: 2026-07-21 | K60: 2026-07-17 | N60: true | Q60: 2/3 | R60: Realizar teste em escala;Realizar teste piloto;Ajustar código | T60: Replicar automação de download para salvar arquivos para a produção
A61: f33MEiU6ukyy7jcLOTwn8GQAAeql | B61: Fechar com fábrica envio dos armários sem gaveta | C61: =_xlfn.XLOOKUP(D61,Buckets!A:A,Buckets!B:B) -> Padronizações/Certificações | D61: jcA3eTZpVESyCtCrwdC8t2QAAqf5 | F61: Concluída | G61: Importante | H61: 1c74a3a3-f72d-417f-97b2-b50d886d5068 | I61: 1c74a3a3-f72d-417f-97b2-b50d886d5068 | J61: 2026-07-22 | K61: 2026-07-24 | L61: 2026-07-20 | N61: false | O61: 2026-07-23 | P61: 1c74a3a3-f72d-417f-97b2-b50d886d5068
A62: 9zblwr9fLE-QywwtpFEvcWQAKiRz | B62: Enviar caixas de celular para unidade de Crato | C62: =_xlfn.XLOOKUP(D62,Buckets!A:A,Buckets!B:B) -> Padronizações/Certificações | D62: jcA3eTZpVESyCtCrwdC8t2QAAqf5 | F62: Concluída | G62: Importante | I62: 1c74a3a3-f72d-417f-97b2-b50d886d5068 | J62: 2026-07-22 | K62: 2026-07-24 | L62: 2026-07-20 | N62: false | O62: 2026-07-23 | P62: c40cc4cc-bdb3-454f-a193-cf3e59051c09
A63: KONvmT0RqUW8D3ZOUnzvNGQAM043 | B63: Montar apresentação sobre o posto de revisão | C63: =_xlfn.XLOOKUP(D63,Buckets!A:A,Buckets!B:B) -> MTM/Impressão 3D | D63: 68oi7tmPFkWnLtIUxxbIyGQAGAus | F63: Concluída | G63: Média | H63: 1c74a3a3-f72d-417f-97b2-b50d886d5068 | I63: 1c74a3a3-f72d-417f-97b2-b50d886d5068 | J63: 2026-07-23 | K63: 2026-07-27 | L63: 2026-07-23 | N63: false | O63: 2026-08-14 | P63: c40cc4cc-bdb3-454f-a193-cf3e59051c09
A64: 2K7dMYi9JEystw4Nj-ykz2QAF_H4 | B64: Criar operação Montar 2 comp. no gabarito sapata | C64: =_xlfn.XLOOKUP(D64,Buckets!A:A,Buckets!B:B) -> MTM/Impressão 3D | D64: 68oi7tmPFkWnLtIUxxbIyGQAGAus | F64: Concluída | G64: Média | H64: 1c74a3a3-f72d-417f-97b2-b50d886d5068 | I64: 1c74a3a3-f72d-417f-97b2-b50d886d5068 | J64: 2026-07-23 | K64: 2026-07-24 | L64: 2026-07-20 | N64: false | O64: 2026-07-23 | P64: 1c74a3a3-f72d-417f-97b2-b50d886d5068
A65: 0HISTDzjREupuKEUBXomwWQAHRPX | B65: [Semana 27-31/07] Melhorias - Semanal F03 | C65: =_xlfn.XLOOKUP(D65,Buckets!A:A,Buckets!B:B) -> RPA | D65: rMSwZXAoc0e0KRod7mGv3mQAO_ax | F65: Concluída | G65: Média | H65: dfffd270-6981-4011-8fa1-759e71d9f99e | I65: dfffd270-6981-4011-8fa1-759e71d9f99e | J65: 2026-07-23 | K65: 2026-07-31 | L65: 2026-07-23 | N65: false | O65: 2026-07-31 | P65: dfffd270-6981-4011-8fa1-759e71d9f99e | Q65: 3/3 | R65: Adicionar dados pendentes;Revisão base para os dados de Volume;Adequar as novas colunas
A66: H3MlmWZ1QEyUZOuOMyiq92QANZ5- | B66: Estudo sobre setup de cor na rotografia | C66: =_xlfn.XLOOKUP(D66,Buckets!A:A,Buckets!B:B) -> SMED | D66: 1XwoBpXjJ02mmuVIAeaTAGQAGr4T | F66: Concluída | G66: Importante | H66: fd56df57-6763-4283-b5e9-97b57478fb7a | I66: fd56df57-6763-4283-b5e9-97b57478fb7a | J66: 2026-07-23 | K66: 2026-07-31 | L66: 2026-07-27 | N66: false | O66: 2026-08-03 | P66: fd56df57-6763-4283-b5e9-97b57478fb7a | Q66: 4/4 | R66: Gravar vídeos de trocas de cor simples e complexas na rotografia;Escolher um produto para fazer análise da carga pendente;Fazer simulação da perda de tempo e custo do setup de acordo com a carga;Analisar possibilidade de fazer melhor sequenciamento de cores.
A67: CVrvPxUjU06TmKhbZjcXwmQAC0dR | B67: [Semana 20-24/07] Robô de alteração de Processos | C67: =_xlfn.XLOOKUP(D67,Buckets!A:A,Buckets!B:B) -> RPA | D67: rMSwZXAoc0e0KRod7mGv3mQAO_ax | F67: Concluída | G67: Média | H67: dfffd270-6981-4011-8fa1-759e71d9f99e | I67: dfffd270-6981-4011-8fa1-759e71d9f99e | J67: 2026-07-23 | K67: 2026-07-24 | N67: false | O67: 2026-07-31 | P67: dfffd270-6981-4011-8fa1-759e71d9f99e | Q67: 4/4 | R67: Mapear atividade de alteração do processo e operações de Base Coating;Criar robô para alteração automatizada;Testes e Revisões no robô;Execução da lista de componentes para alteração
A68: uOQd15wA7ku_i9V9PqU_FmQAPAh8 | B68: Definição de Padrão (Capacidade) das esteiras do CD. | C68: =_xlfn.XLOOKUP(D68,Buckets!A:A,Buckets!B:B) -> Logística | D68: hzRxxQYRwUmjMGwIgIiUvGQABgeH | F68: Concluída | G68: Média | H68: 13401436-5972-4968-9178-08d3bcd592a4 | I68: c40cc4cc-bdb3-454f-a193-cf3e59051c09 | J68: 2026-07-23 | K68: 2026-07-24 | N68: false | O68: 2026-07-23 | P68: c40cc4cc-bdb3-454f-a193-cf3e59051c09
A69: zTEdatnkPUWYyj2qrOs7WWQAF7FB | B69: Análise de layout das salas de tintas para recebimento dos contêiner de adesivo. | C69: =_xlfn.XLOOKUP(D69,Buckets!A:A,Buckets!B:B) -> Logística | D69: hzRxxQYRwUmjMGwIgIiUvGQABgeH | F69: Concluída | G69: Média | H69: 13401436-5972-4968-9178-08d3bcd592a4 | I69: c40cc4cc-bdb3-454f-a193-cf3e59051c09 | J69: 2026-07-23 | N69: false | O69: 2026-07-23 | P69: c40cc4cc-bdb3-454f-a193-cf3e59051c09
A70: YaEnYWINY0iGZiTRFh-SgWQAIjcR | B70: Plano de comunicação do Programa de Melhorias - Gerencias e Coordenadores | C70: =_xlfn.XLOOKUP(D70,Buckets!A:A,Buckets!B:B) -> Programa de Melhorias | D70: NHhoi0Q460Owj98eJ_OOMmQANgsZ | F70: Não iniciado | G70: Média | H70: 05f35150-a826-4040-9362-c540d816ffd0 | I70: 05f35150-a826-4040-9362-c540d816ffd0 | J70: 2026-07-23 | K70: 2026-08-15 | L70: 2026-08-10 | N70: false | Q70: 2/2 | R70: Estruturar material e criar o plano de comunicação para Gerentes e Coordenadores;Cronograma de Apresentação do Material - Programa de Melhorias - Conteúdo e Aderência
A71: A8URaDb6EESh35VGQ1yc5mQABR88 | B71: Estudo - Setup de Cor | C71: =_xlfn.XLOOKUP(D71,Buckets!A:A,Buckets!B:B) -> SMED | D71: 1XwoBpXjJ02mmuVIAeaTAGQAGr4T | F71: Em andamento | G71: Média | H71: 58a13380-4d77-41ea-9406-2f4cb7f6bd8c | I71: 58a13380-4d77-41ea-9406-2f4cb7f6bd8c | J71: 2026-07-23 | K71: 2026-08-07 | N71: true | Q71: 5/5 | R71: Levantar quantidade de PP/Líder Técnico por turno;Criar mapa de raciocínio do setup de cor para investigar as causas do acumulo de tempo;Verificar quantidade de setups simples e complexos por turno;Analisar os resultado dos tempos de Setup de Cor (estratificado);Acompanhar setups de cor
A72: iUqxskDAfk2VERuMOQ5KiGQAEbH8 | B72: Criação do Video do Evento do Programa de Melhorias | C72: =_xlfn.XLOOKUP(D72,Buckets!A:A,Buckets!B:B) -> Programa de Melhorias | D72: NHhoi0Q460Owj98eJ_OOMmQANgsZ | F72: Concluída | G72: Importante | H72: 05f35150-a826-4040-9362-c540d816ffd0 | I72: 05f35150-a826-4040-9362-c540d816ffd0 | J72: 2026-07-23 | K72: 2026-07-31 | L72: 2026-07-27 | N72: false | O72: 2026-07-31 | P72: 05f35150-a826-4040-9362-c540d816ffd0 | Q72: 0/1 | R72: Finalizar edição do vídeo do Evento de Melhorias
A73: 9qD0NlOdtE6VRfIRsssna2QAAHId | B73: Criar cronograma de Passadas com Supervisores da Engenharia - Manoel | C73: =_xlfn.XLOOKUP(D73,Buckets!A:A,Buckets!B:B) -> RPA | D73: rMSwZXAoc0e0KRod7mGv3mQAO_ax | F73: Concluída | G73: Importante | H73: 05f35150-a826-4040-9362-c540d816ffd0 | I73: 05f35150-a826-4040-9362-c540d816ffd0 | J73: 2026-07-23 | K73: 2026-07-31 | L73: 2026-07-27 | N73: false | O73: 2026-08-06 | P73: 05f35150-a826-4040-9362-c540d816ffd0
A74: Ia8IBp08ZEygk65zYtgGS2QACnKh | B74: Análise Engate de Escoamento (Dosador) | C74: =_xlfn.XLOOKUP(D74,Buckets!A:A,Buckets!B:B) -> SMED | D74: 1XwoBpXjJ02mmuVIAeaTAGQAGr4T | F74: Em andamento | G74: Média | H74: 58a13380-4d77-41ea-9406-2f4cb7f6bd8c | I74: 58a13380-4d77-41ea-9406-2f4cb7f6bd8c | J74: 2026-07-23 | K74: 2026-07-31 | N74: true | Q74: 0/4 | R74: Caso necessário, estudar novo protótipo para substituir o atual;Analisar modificação do protótipo atual;Pensar novo método para evitar descer da máquina com peso (matéria prima em excesso);Readequação do engate atual
A75: eRjP6tBFjkGUNrZ_bgTDPWQAEMX9 | B75: Estruturar com as áreas sobre a Embalagem para o momento da Hora da Excelência | C75: =_xlfn.XLOOKUP(D75,Buckets!A:A,Buckets!B:B) -> Padronizações/Certificações | D75: jcA3eTZpVESyCtCrwdC8t2QAAqf5 | F75: Não iniciado | G75: Média | H75: 05f35150-a826-4040-9362-c540d816ffd0 | I75: 05f35150-a826-4040-9362-c540d816ffd0 | J75: 2026-07-23 | K75: 2026-08-15 | L75: 2026-07-27 | N75: false
A76: aakzS-Auz0iP8i-K-YluAmQAFq5E | B76: 22/07 - Reunião de Indicadores dos Montadores | C76: =_xlfn.XLOOKUP(D76,Buckets!A:A,Buckets!B:B) -> Pendências Fechamento de Indicadores | D76: X4rT7zMEMUaVaYHT5_sXtWQAMXMy | F76: Não iniciado | G76: Média | I76: c40cc4cc-bdb3-454f-a193-cf3e59051c09 | J76: 2026-07-23 | K76: 2026-08-07 | N76: true | Q76: 0/1 | R76: Cronograma dos vídeos do Programa de Melhorias
A77: YuFczN61RUKxveXsNdFoa2QABRdG | B77: 16/07 - Fechamento de Indicadores dos Transformadores | C77: =_xlfn.XLOOKUP(D77,Buckets!A:A,Buckets!B:B) -> Pendências Fechamento de Indicadores | D77: X4rT7zMEMUaVaYHT5_sXtWQAMXMy | F77: Não iniciado | G77: Média | I77: c40cc4cc-bdb3-454f-a193-cf3e59051c09 | J77: 2026-07-23 | K77: 2026-08-07 | N77: true | Q77: 0/6 | R77: Analisar complexidade da injeção de Fortaleza comparando com Sobral, resultados de OPE.;Comparativo de ineficiência da injeção full com expandido;Acompanhar implantação do SIMON na injeção de EVA;Apresentar quantidade de melhorias do grupo de inelegíveis;Separar os produtos com matrizes novas nos blocos das ineficiências.;Analisar ajuste de meta da injeção de Crato
A78: nfOLeiVx7EGZbEB9egTTjGQAGoDc | B78: Abertura de Solicitação de licença para IA - Para criação de vídeos HeyGEn | C78: =_xlfn.XLOOKUP(D78,Buckets!A:A,Buckets!B:B) -> Programa de Melhorias | D78: NHhoi0Q460Owj98eJ_OOMmQANgsZ | F78: Concluída | G78: Média | H78: 05f35150-a826-4040-9362-c540d816ffd0 | I78: 05f35150-a826-4040-9362-c540d816ffd0 | J78: 2026-07-24 | K78: 2026-07-23 | L78: 2026-07-23 | N78: false | O78: 2026-07-24 | P78: 05f35150-a826-4040-9362-c540d816ffd0 | T78: Foi solicitado ao Renan Grabo o levantamento das IA com o objetivo de criação de vídeos e o mesmo realizou o levantamento. Valor
A79: Gq17wQxRgESknNCzCUcW8WQABvJb | B79: AMR para entrega de insumos (Sala de Tintas) | C79: =_xlfn.XLOOKUP(D79,Buckets!A:A,Buckets!B:B) -> MOI, MOA, MODS | D79: QKOg4Hdgj0ivgeBuZ62ybmQAI-jH | F79: Não iniciado | G79: Média | I79: 8c3f18d2-9083-4819-8529-3d7d7f9bfbda | J79: 2026-07-25 | N79: false
A80: bYSBzwl280uSIRXISLKFq2QAEy0t | B80: POP da troca de número na rotografia friso | C80: =_xlfn.XLOOKUP(D80,Buckets!A:A,Buckets!B:B) -> SMED | D80: 1XwoBpXjJ02mmuVIAeaTAGQAGr4T | F80: Concluída | G80: Média | H80: fd56df57-6763-4283-b5e9-97b57478fb7a | I80: fd56df57-6763-4283-b5e9-97b57478fb7a | J80: 2026-07-28 | K80: 2026-07-28 | N80: false | O80: 2026-07-28 | P80: fd56df57-6763-4283-b5e9-97b57478fb7a
A81: 26dsmOCXAEeQi41emCT2ZmQAGXzw | B81: Estudos - Sala de Amostras | C81: =_xlfn.XLOOKUP(D81,Buckets!A:A,Buckets!B:B) -> SMED | D81: 1XwoBpXjJ02mmuVIAeaTAGQAGr4T | F81: Em andamento | G81: Importante | H81: 58a13380-4d77-41ea-9406-2f4cb7f6bd8c;07a2aff1-4a07-48ba-8ada-daf14a19fd85 | I81: 58a13380-4d77-41ea-9406-2f4cb7f6bd8c | J81: 2026-07-29 | K81: 2026-08-21 | L81: 2026-07-21 | N81: false | Q81: 7/8 | R81: Implementar pastas nas máquinas;Acompanhamento: pastas sendo utilizadas no novo formato (Acompanhar no físico);Aprofundamento na análise do histórico de solicitações dos kits (Solicitação André);Definir quantidade de pastas necessárias para compra;Análise do histórico de solicitações de kits;Protótipo de layout;Medição Sala de revisão x Sala de amostra;Implementação: realocação de pastas com divisórias
A82: o7wTpgviUkibX92RQKooLWQAOo1A | B82: Fazer análise da troca de caixa preparação com elevador | C82: =_xlfn.XLOOKUP(D82,Buckets!A:A,Buckets!B:B) -> MTM/Impressão 3D | D82: 68oi7tmPFkWnLtIUxxbIyGQAGAus | F82: Concluída | G82: Média | H82: 1c74a3a3-f72d-417f-97b2-b50d886d5068 | I82: 1c74a3a3-f72d-417f-97b2-b50d886d5068 | J82: 2026-07-30 | K82: 2026-07-31 | L82: 2026-07-27 | N82: false | O82: 2026-07-31 | P82: c40cc4cc-bdb3-454f-a193-cf3e59051c09
A83: 9BsFcrppZ0GNy5dAH1A8wGQAMbUC | B83: Fazer análise do apontamento SIMON Setup | C83: =_xlfn.XLOOKUP(D83,Buckets!A:A,Buckets!B:B) -> MTM/Impressão 3D | D83: 68oi7tmPFkWnLtIUxxbIyGQAGAus | F83: Concluída | G83: Média | H83: 1c74a3a3-f72d-417f-97b2-b50d886d5068 | I83: 1c74a3a3-f72d-417f-97b2-b50d886d5068 | J83: 2026-07-30 | K83: 2026-07-31 | L83: 2026-07-27 | N83: false | O83: 2026-07-31 | P83: c40cc4cc-bdb3-454f-a193-cf3e59051c09
A84: OR3EECFgIUGH8MdHCrB-rGQAE-F1 | B84: Fazer análise apontamento SIMON Disponibilidade | C84: =_xlfn.XLOOKUP(D84,Buckets!A:A,Buckets!B:B) -> MTM/Impressão 3D | D84: 68oi7tmPFkWnLtIUxxbIyGQAGAus | F84: Concluída | G84: Média | H84: 1c74a3a3-f72d-417f-97b2-b50d886d5068 | I84: 1c74a3a3-f72d-417f-97b2-b50d886d5068 | J84: 2026-07-30 | K84: 2026-07-31 | L84: 2026-07-27 | N84: false | O84: 2026-07-31 | P84: c40cc4cc-bdb3-454f-a193-cf3e59051c09
A85: LuppmLo5wEWxlAY53tYdKmQAFXe9 | B85: Fazer a solicitação do Usuario da IA HeyGEn - Para produção de Videos do Programa de Melhorias | C85: =_xlfn.XLOOKUP(D85,Buckets!A:A,Buckets!B:B) -> Programa de Melhorias | D85: NHhoi0Q460Owj98eJ_OOMmQANgsZ | F85: Concluída | G85: Importante | I85: 05f35150-a826-4040-9362-c540d816ffd0 | J85: 2026-07-30 | K85: 2026-07-31 | L85: 2026-07-20 | N85: false | O85: 2026-07-30 | P85: 05f35150-a826-4040-9362-c540d816ffd0
A86: RnOEoxFvm0W2IL5gFQ49eGQAOe25 | B86: Revisar análise - Unir Tira, enformar prensar e desenformar - sorveteira a vácuo | C86: =_xlfn.XLOOKUP(D86,Buckets!A:A,Buckets!B:B) -> MTM/Impressão 3D | D86: 68oi7tmPFkWnLtIUxxbIyGQAGAus | F86: Concluída | G86: Média | H86: 1c74a3a3-f72d-417f-97b2-b50d886d5068 | I86: 1c74a3a3-f72d-417f-97b2-b50d886d5068 | J86: 2026-07-30 | K86: 2026-07-31 | L86: 2026-07-27 | N86: false | O86: 2026-07-31 | P86: c40cc4cc-bdb3-454f-a193-cf3e59051c09
A87: L3GVZ9BgwUS52DIPmFLnNGQAF0JA | B87: Revisar análise - Aplicar Cola em sola, Área de Colagem da palmilha, Sola Cape Gaspea Adulto | C87: =_xlfn.XLOOKUP(D87,Buckets!A:A,Buckets!B:B) -> MTM/Impressão 3D | D87: 68oi7tmPFkWnLtIUxxbIyGQAGAus | F87: Concluída | G87: Média | H87: 1c74a3a3-f72d-417f-97b2-b50d886d5068 | I87: 1c74a3a3-f72d-417f-97b2-b50d886d5068 | J87: 2026-07-30 | K87: 2026-07-31 | L87: 2026-07-27 | N87: false | O87: 2026-07-31 | P87: c40cc4cc-bdb3-454f-a193-cf3e59051c09
A88: nx6ETudwhkSZKF-DlV9LdmQAMmMc | B88: Liberar análise - Unir palmilha em cabedal com sola plataforma EVA + Enformar, Prensar e Desenformar, Sorveteira, Obter forma sem dedeira e Obter cabedal da esteira, Cabedal Com Tira de Fech | C88: =_xlfn.XLOOKUP(D88,Buckets!A:A,Buckets!B:B) -> MTM/Impressão 3D | D88: 68oi7tmPFkWnLtIUxxbIyGQAGAus | F88: Concluída | G88: Média | H88: 1c74a3a3-f72d-417f-97b2-b50d886d5068 | I88: 1c74a3a3-f72d-417f-97b2-b50d886d5068 | J88: 2026-07-30 | K88: 2026-07-31 | L88: 2026-07-27 | N88: false | O88: 2026-07-31 | P88: c40cc4cc-bdb3-454f-a193-cf3e59051c09
A89: 1ddPje12i0ShFE3QmIWCtGQADlMD | B89: Criar análise - Passar sola pelo termoget, sola baixa, obter e dispor na esteira + Retirar fio de cola palmilha | C89: =_xlfn.XLOOKUP(D89,Buckets!A:A,Buckets!B:B) -> MTM/Impressão 3D | D89: 68oi7tmPFkWnLtIUxxbIyGQAGAus | F89: Concluída | G89: Média | H89: 1c74a3a3-f72d-417f-97b2-b50d886d5068 | I89: 1c74a3a3-f72d-417f-97b2-b50d886d5068 | J89: 2026-07-30 | K89: 2026-07-31 | L89: 2026-07-27 | N89: false | O89: 2026-07-31 | P89: c40cc4cc-bdb3-454f-a193-cf3e59051c09
A90: IQagZw7PYEuAexzyqYIbdmQAHy6h | B90: Imprimir e Enviar formas do modelo 38154 para Fortaleza | C90: =_xlfn.XLOOKUP(D90,Buckets!A:A,Buckets!B:B) -> MTM/Impressão 3D | D90: 68oi7tmPFkWnLtIUxxbIyGQAGAus | F90: Concluída | G90: Média | H90: 1c74a3a3-f72d-417f-97b2-b50d886d5068 | I90: 1c74a3a3-f72d-417f-97b2-b50d886d5068 | J90: 2026-07-30 | K90: 2026-07-31 | L90: 2026-07-27 | N90: false | O90: 2026-07-31 | P90: c40cc4cc-bdb3-454f-a193-cf3e59051c09
A91: 8KsST1BOoEK6Pf8uBKz-_WQAH0WU | B91: Ações de Planejamento Programa de Melhorias Mai-Jun26 | C91: =_xlfn.XLOOKUP(D91,Buckets!A:A,Buckets!B:B) -> Programa de Melhorias | D91: NHhoi0Q460Owj98eJ_OOMmQANgsZ | F91: Concluída | G91: Média | H91: 05f35150-a826-4040-9362-c540d816ffd0 | I91: 05f35150-a826-4040-9362-c540d816ffd0 | J91: 2026-07-30 | K91: 2026-08-10 | L91: 2026-08-01 | N91: false | O91: 2026-08-14 | P91: 05f35150-a826-4040-9362-c540d816ffd0 | Q91: 6/6 | R91: Impressão dos Certificados;Criação da Apresentação do Evento;Impressão dos Cartões dos Premiados;Vídeo de Comunicação - Programa de Melhorias;Requisição dos calçados Programa de Melhorias - 03/08/2026;Requisição dos calçados Indicadores Internos - 29/07/2026
A92: RQwDVlQdsUCAhihPeHJq82QAO_BU | B92: Desenhar e imprimir bases para placas laboratório | C92: =_xlfn.XLOOKUP(D92,Buckets!A:A,Buckets!B:B) -> MTM/Impressão 3D | D92: 68oi7tmPFkWnLtIUxxbIyGQAGAus | F92: Concluída | G92: Média | H92: 1c74a3a3-f72d-417f-97b2-b50d886d5068 | I92: 1c74a3a3-f72d-417f-97b2-b50d886d5068 | J92: 2026-07-30 | K92: 2026-07-31 | L92: 2026-07-27 | N92: false | O92: 2026-07-31 | P92: c40cc4cc-bdb3-454f-a193-cf3e59051c09
A93: e_DhwMFXfkyGs6sRang6fGQAKO7a | B93: Revisar análise - Unir dedeira e palmilha no cabedal EVA, obter sola com palmilha já preso da esteira, dispor na esteira | C93: =_xlfn.XLOOKUP(D93,Buckets!A:A,Buckets!B:B) -> MTM/Impressão 3D | D93: 68oi7tmPFkWnLtIUxxbIyGQAGAus | F93: Concluída | G93: Média | H93: 1c74a3a3-f72d-417f-97b2-b50d886d5068 | I93: 1c74a3a3-f72d-417f-97b2-b50d886d5068 | J93: 2026-07-30 | K93: 2026-07-31 | L93: 2026-07-27 | N93: false | O93: 2026-07-31 | P93: c40cc4cc-bdb3-454f-a193-cf3e59051c09
A94: IO8hRZVgcES2pP2D1qDU-2QAOXzT | B94: Fechar indicadores de Julho e Criar indicadores de Agosto | C94: =_xlfn.XLOOKUP(D94,Buckets!A:A,Buckets!B:B) -> Pendências Fechamento de Indicadores | D94: X4rT7zMEMUaVaYHT5_sXtWQAMXMy | F94: Concluída | G94: Média | H94: 1c74a3a3-f72d-417f-97b2-b50d886d5068 | I94: 1c74a3a3-f72d-417f-97b2-b50d886d5068 | J94: 2026-07-31 | K94: 2026-08-07 | L94: 2026-08-03 | N94: false | O94: 2026-08-14 | P94: c40cc4cc-bdb3-454f-a193-cf3e59051c09 | Q94: 11/13 | R94: Melhoria TC;Auditoria 5S;Banco de Horas;Aprov. Estrutura Melissa;Passada Horizontal;Auditoria Produto Certificado;Melhoria MP;Aprov. Estrutura;Aderência MTM Melissa;Ineficiência;Aderência MTM;Certificação De produtos;Inclusão de batida
A95: EXBWHiRVBEiEsWb3GQzPnmQAIJGM | B95: Revisar análise - Limpar fio de cola, área da palmilha, com pincel, bico e calcanhar, obter simultâneo da esteira e dispor simultâneo, AD/INF | C95: =_xlfn.XLOOKUP(D95,Buckets!A:A,Buckets!B:B) -> MTM/Impressão 3D | D95: 68oi7tmPFkWnLtIUxxbIyGQAGAus | F95: Concluída | G95: Média | H95: 1c74a3a3-f72d-417f-97b2-b50d886d5068 | I95: 1c74a3a3-f72d-417f-97b2-b50d886d5068 | J95: 2026-07-31 | K95: 2026-07-31 | L95: 2026-07-27 | N95: false | O95: 2026-07-31 | P95: c40cc4cc-bdb3-454f-a193-cf3e59051c09
A96: pcpJf9LytE6xf1yc5CQFg2QAFgYS | B96: Criar análise - Embutir cabedal na palmilha, 1 Dedeira + Aplicar Cola na Dedeira 3 áreas, com Bico de Pato Simples, Obter da esteira, Par | C96: =_xlfn.XLOOKUP(D96,Buckets!A:A,Buckets!B:B) -> MTM/Impressão 3D | D96: 68oi7tmPFkWnLtIUxxbIyGQAGAus | F96: Concluída | G96: Média | H96: 1c74a3a3-f72d-417f-97b2-b50d886d5068 | I96: 1c74a3a3-f72d-417f-97b2-b50d886d5068 | J96: 2026-07-31 | K96: 2026-07-31 | L96: 2026-07-27 | N96: false | O96: 2026-07-31 | P96: c40cc4cc-bdb3-454f-a193-cf3e59051c09
A97: sbymhEvYZESsUZHJp03GD2QAFOku | B97: Acompanhamento de PPPs na hora das trocas de cor para verificar se realmente há problemas com o robô | C97: =_xlfn.XLOOKUP(D97,Buckets!A:A,Buckets!B:B) -> SMED | D97: 1XwoBpXjJ02mmuVIAeaTAGQAGr4T | F97: Concluída | G97: Média | H97: fd56df57-6763-4283-b5e9-97b57478fb7a | I97: fd56df57-6763-4283-b5e9-97b57478fb7a | J97: 2026-07-31 | K97: 2026-07-31 | L97: 2026-07-27 | N97: false | O97: 2026-07-31 | P97: fd56df57-6763-4283-b5e9-97b57478fb7a
A98: rNBhsyV_rUu6f7HcsUjo_mQAL8R3 | B98: Reunião com PPPs sobre custo do setup e premiação SMED | C98: =_xlfn.XLOOKUP(D98,Buckets!A:A,Buckets!B:B) -> SMED | D98: 1XwoBpXjJ02mmuVIAeaTAGQAGr4T | F98: Em andamento | G98: Média | H98: fd56df57-6763-4283-b5e9-97b57478fb7a | I98: fd56df57-6763-4283-b5e9-97b57478fb7a | J98: 2026-07-31 | K98: 2026-08-13 | L98: 2026-07-20 | N98: true | Q98: 5/6 | R98: Fábrica 6 - 2° turno;Fábrica 1 - 2° turno;Fábrica 7 - 2° turno;Fábrica 6 - 1° turno;Fábrica 1 - 1° turno;Fábrica 7 - 1° turno
A99: ZjAN4YBVIESVi-rcfclTBWQADyss | B99: MOI - Sala de Tintas | C99: =_xlfn.XLOOKUP(D99,Buckets!A:A,Buckets!B:B) -> MOI, MOA, MODS | D99: QKOg4Hdgj0ivgeBuZ62ybmQAI-jH | F99: Não iniciado | G99: Importante | H99: 8c3f18d2-9083-4819-8529-3d7d7f9bfbda | I99: 8c3f18d2-9083-4819-8529-3d7d7f9bfbda | J99: 2026-07-31 | K99: 2026-08-28 | L99: 2026-08-03 | N99: false | Q99: 0/7 | R99: Mapear todas as atividades realizadas na área e funções;Apresentar e validar com a gestão;Nova proposta de dimensionamento;Levantamento da situação atual;Testar nova proposta de dimensionamento;Lançar FAP;Verificar possíveis melhorias ou automações de processos | S99: Crato
A100: RY5Q6Ny2L0Wf47VKIVIN_GQAEBW- | B100: Acompanhar a aplicação dos Manifolds - Troca Rápida de Ar | C100: =_xlfn.XLOOKUP(D100,Buckets!A:A,Buckets!B:B) -> SMED | D100: 1XwoBpXjJ02mmuVIAeaTAGQAGr4T | F100: Não iniciado | G100: Média | H100: da78ac04-7f85-4d9a-afb4-9b5876e9062b | I100: da78ac04-7f85-4d9a-afb4-9b5876e9062b | J100: 2026-07-31 | K100: 2026-08-07 | L100: 2026-08-03 | N100: true | Q100: 0/3 | R100: Gravar trocas utilizando o Manifold;Apresentar os resultados - Análise ECRS;Acompanhar a entrega de 26 Manifold's para os Trocadores | S100: Fortaleza
...

Sheet Metas
A1: ID da Meta | B1: Nome da meta | C1: Status | D1: Prioridade | E1: Data de início | F1: Data de término | G1: Tarefas conectadas | H1: Notas
A2: _TclC5XyU0itQqOSRgoOa2QAB9Fw | B2: Atingir 85% de aderência no Programa de Melhorias | C2: No prazo | D2: 5 | G2: Credenciamento - Programa de Melhorias
A3: CPyA7_JXT0Ot246svFbgKWQADc9O | B3: Redução de 25% do tempo de setup de matriz e 15% setup de cor na injeção de EVA | C3: No prazo | D3: 5 | G3: Otimização Setup Matriz EVA;SMED Setup de Cor EVA
A4: UIsKR4azC0aIhKUlTIZKCWQAAOHD | B4: Redução de 50 efetivos MOA, MOI e MODS | C4: No prazo | D4: 5 | F4: 2026-11-06 | G4: MOI - Movimentadores de Caixas Montagem;MOI - Auxiliar de Matrizaria;MOI - Matrizeiro;MOI - Tegad / Célula de Layout;Projeto TR Cabine de Pintura Manual;Projeto 02 - Dimensionamento dos Trocadores de Layout Fáb. 06;Projeto 02 - Dimensionamento dos Trocadores de Layout Fáb. 07;Projeto 02 - Dimensionamento dos Trocadores de Layout Crato;Projeto 02 - Dimensionamento dos Trocadores de Layout Fáb. 01;Projeto 01 - Dimensionamento dos Reguladores de Telas

Sheet Buckets
A1: ID de Bucket | B1: Nome do Bucket
A2: QKOg4Hdgj0ivgeBuZ62ybmQAI-jH | B2: MOI, MOA, MODS
A3: 1XwoBpXjJ02mmuVIAeaTAGQAGr4T | B3: SMED
A4: rMSwZXAoc0e0KRod7mGv3mQAO_ax | B4: RPA
A5: 68oi7tmPFkWnLtIUxxbIyGQAGAus | B5: MTM/Impressão 3D
A6: jcA3eTZpVESyCtCrwdC8t2QAAqf5 | B6: Padronizações/Certificações
A7: NHhoi0Q460Owj98eJ_OOMmQANgsZ | B7: Programa de Melhorias
A8: hzRxxQYRwUmjMGwIgIiUvGQABgeH | B8: Logística
A9: KIfHiHgMjUeezxBeVZXLlmQABdnJ | B9: Melhorias do Bimestre | C9: Programa de Melhorias | D9: Tarefas Antigas
A10: X4rT7zMEMUaVaYHT5_sXtWQAMXMy | B10: Pendências Fechamento de Indicadores

Sheet Usuários
A1: ID do Usuário | B1: Nome do usuário | C1: Email
A2: 63dd591c-960d-4c36-ad48-5b9197dc40ea | B2: Francisco Romulo de Aguiar | C2: romulo.aguiar@grendene.com.br
A3: 3a4654ae-d002-45f0-a510-5a3d7e37c058 | B3: William Kennedy Rodrigues Lopes | C3: william.lopes@grendene.com.br
A4: 13401436-5972-4968-9178-08d3bcd592a4 | B4: Francisco Martins da Silva | C4: martins.silva@grendene.com.br
A5: 8c3f18d2-9083-4819-8529-3d7d7f9bfbda | B5: Charliane Batista de Alencar | C5: charlianeb.alencar@grendene.com.br
A6: c40cc4cc-bdb3-454f-a193-cf3e59051c09 | B6: Fernanda Sousa Araujo | C6: fernanda.araujo@grendene.com.br
A7: 07a2aff1-4a07-48ba-8ada-daf14a19fd85 | B7: Aliny Kelly De Assis Rufino | C7: aliny.rufino@grendene.com.br
A8: 05f35150-a826-4040-9362-c540d816ffd0 | B8: Leonardo Costa da Silva | C8: silva.leonardo@grendene.com.br
A9: 9686d721-f970-4664-808d-2b7eccd6564a | B9: Thiago Roberto Andrade Aguiar | C9: roberto.aguiar@grendene.com.br
A10: 1c74a3a3-f72d-417f-97b2-b50d886d5068 | B10: Leonardo Galdino de Oliveira | C10: leonardo.oliveir@grendene.com.br
A11: dfffd270-6981-4011-8fa1-759e71d9f99e | B11: Nalbert de Matos Vieira | C11: nalbert.vieira@grendene.com.br
A12: 58a13380-4d77-41ea-9406-2f4cb7f6bd8c | B12: Daniel Viana de Carvalho | C12: daniel.carvalho@grendene.com.br
A13: da78ac04-7f85-4d9a-afb4-9b5876e9062b | B13: Alan Feitosa Vilela | C13: alan.vilela@grendene.com.br

Sheet Planilha1
A1: Descrição | B1: Sigla
A2: Melhorias do Bimestre | B2: MEL/BI
A3: MOI, MOA, MODS | B3: KPI
A4: SMED | B4: SMED
A5: Programa de Melhorias | B5: PG/MEL
A6: Padronizações/Certificações | B6: PD/CERT
A7: MTM/Impressão 3D | B7: MTM/3D
A8: RPA | B8: RPA
A9: Logística | B9: LOG
A10: Pendências Fechamento de Indicadores | B10: PEND
